{
  "AeroMeshData": "<unsupported: SharedString(SharedString { data: Some([]), hash: Hash(\"af1349b9f5f9a1a6a0404dea36dcc9499bcb25c9adc112b7cc9a93cae41f3262\") })>",
  "Anchored": false,
  "Attributes": "<unsupported: Attributes(Attributes { data: {} })>",
  "AudioCanCollide": true,
  "BackParamA": -0.5,
  "BackParamB": 0.5,
  "BackSurface": "<unsupported: Enum(Enum { value: 0 })>",
  "BackSurfaceInput": "<unsupported: Enum(Enum { value: 0 })>",
  "BottomParamA": -0.5,
  "BottomParamB": 0.5,
  "BottomSurface": "<unsupported: Enum(Enum { value: 0 })>",
  "BottomSurfaceInput": "<unsupported: Enum(Enum { value: 0 })>",
  "CFrame": {
    "matrix": {
      "orientation": [
        [
          1.0,
          0.0,
          0.0
        ],
        [
          0.0,
          1.0,
          0.0
        ],
        [
          0.0,
          0.0,
          1.0
        ]
      ],
      "position": [
        9.411933898925781,
        0.45640799403190613,
        -91.5113525390625
      ]
    }
  },
  "CanCollide": true,
  "CanQuery": true,
  "CanTouch": true,
  "Capabilities": "<unsupported: SecurityCapabilities(SecurityCapabilities { value: 0 })>",
  "CastShadow": true,
  "CollisionGroup": "Default",
  "CollisionGroupId": 0,
  "Color": "<unsupported: Color3uint8(Color3uint8 { r: 163, g: 162, b: 165 })>",
  "CustomPhysicalProperties": "<unsupported: PhysicalProperties(Default)>",
  "DoubleSided": false,
  "EnableFluidForces": true,
  "FluidFidelityInternal": "<unsupported: Enum(Enum { value: 0 })>",
  "FrontParamA": -0.5,
  "FrontParamB": 0.5,
  "FrontSurface": "<unsupported: Enum(Enum { value: 0 })>",
  "FrontSurfaceInput": "<unsupported: Enum(Enum { value: 0 })>",
  "HasJointOffset": false,
  "HasSkinnedMesh": false,
  "HistoryId": "<unsupported: UniqueId(UniqueId { index: 0, time: 0, random: 0 })>",
  "InertiaMigrated": false,
  "InitialSize": {
    "x": 0.49933499097824097,
    "y": 0.9130069613456726,
    "z": 0.5084689855575562
  },
  "JointOffset": {
    "x": 0.0,
    "y": 0.0,
    "z": 0.0
  },
  "LeftParamA": -0.5,
  "LeftParamB": 0.5,
  "LeftSurface": "<unsupported: Enum(Enum { value: 0 })>",
  "LeftSurfaceInput": "<unsupported: Enum(Enum { value: 0 })>",
  "Locked": false,
  "Massless": false,
  "Material": "<unsupported: Enum(Enum { value: 256 })>",
  "MaterialVariant": "",
  "MeshContent": "<unsupported: Content(Content(Uri(\"rbxassetid://3557782828\")))>",
  "PhysicalConfigData": "<unsupported: SharedString(SharedString { data: Some([67, 83, 71, 80, 72, 83, 6, 0, 0, 0, 243, 138, 136, 61, 153, 144, 62, 58, 173, 120, 130, 190, 245, 71, 56, 185, 56, 100, 64, 59, 144, 97, 243, 182, 0, 224, 190, 50, 20, 136, 235, 58, 0, 136, 183, 53, 236, 249, 62, 59, 16, 0, 0, 0, 0, 0, 0, 0, 0, 0, 0, 0, 0, 0, 0, 0, 0, 0, 0, 0, 16, 0, 0, 0, 0, 0, 0, 0, 0, 0, 0, 0, 0, 0, 0, 0, 0, 0, 128, 63, 108, 0, 0, 0, 4, 0, 0, 0, 0, 128, 129, 57, 192, 189, 105, 62, 4, 30, 215, 188, 0, 128, 129, 57, 131, 161, 157, 62, 121, 177, 127, 189, 124, 133, 77, 60, 192, 189, 105, 62, 154, 152, 188, 188, 0, 128, 129, 57, 192, 189, 105, 62, 248, 85, 204, 60, 0, 128, 129, 57, 202, 41, 172, 62, 64, 31, 150, 189, 146, 182, 20, 61, 183, 44, 172, 62, 105, 163, 130, 189, 88, 187, 252, 60, 250, 162, 157, 62, 180, 138, 94, 189, 252, 244, 118, 60, 192, 189, 105, 62, 166, 31, 168, 188, 148, 229, 80, 60, 192, 189, 105, 62, 111, 77, 176, 60, 221, 65, 0, 61, 21, 179, 157, 62, 200, 255, 86, 61, 64, 17, 0, 58, 140, 180, 157, 62, 0, 125, 121, 61, 0, 128, 129, 57, 140, 180, 157, 62, 86, 80, 121, 61, 0, 128, 129, 57, 203, 68, 175, 62, 34, 211, 147, 189, 24, 106, 18, 61, 166, 74, 175, 62, 47, 169, 128, 189, 134, 120, 100, 61, 166, 74, 175, 62, 142, 244, 47, 189, 13, 238, 128, 61, 165, 47, 172, 62, 96, 251, 24, 189, 78, 115, 91, 61, 231, 165, 157, 62, 20, 151, 2, 189, 50, 205, 180, 60, 192, 189, 105, 62, 69, 124, 94, 188, 24, 192, 121, 60, 192, 189, 105, 62, 180, 182, 155, 60, 210, 149, 92, 61, 39, 176, 157, 62, 109, 119, 244, 60, 65, 229, 22, 61, 73, 62, 172, 62, 202, 68, 125, 61, 64, 26, 13, 58, 192, 63, 172, 62, 32, 246, 146, 61, 0, 128, 129, 57, 248, 203, 157, 62, 200, 154, 121, 61, 222, 72, 223, 60, 166, 74, 175, 62, 250, 57, 133, 189, 0, 128, 129, 57, 166, 74, 175, 62, 87, 125, 144, 61, 6, 231, 125, 61, 166, 74, 175, 62, 179, 182, 22, 189, 106, 222, 146, 61, 166, 74, 175, 62, 40, 100, 151, 186, 113, 35, 149, 61, 128, 53, 172, 62, 181, 135, 149, 186, 174, 208, 125, 61, 195, 171, 157, 62, 117, 57, 140, 186, 20, 4, 210, 60, 192, 189, 105, 62, 154, 43, 89, 186, 93, 217, 181, 60, 192, 189, 105, 62, 154, 128, 68, 60, 168, 149, 129, 61, 92, 59, 172, 62, 29, 11, 16, 61, 198, 152, 20, 61, 166, 74, 175, 62, 29, 110, 121, 61, 0, 128, 129, 57, 192, 63, 172, 62, 4, 194, 146, 61, 192, 61, 11, 58, 166, 74, 175, 62, 2, 170, 144, 61, 60, 54, 127, 61, 166, 74, 175, 62, 113, 198, 13, 61, 204, 0, 0, 0, 0, 0, 0, 0, 1, 0, 0, 0, 2, 0, 0, 0, 0, 0, 0, 0, 2, 0, 0, 0, 7, 0, 0, 0, 0, 0, 0, 0, 7, 0, 0, 0, 17, 0, 0, 0, 0, 0, 0, 0, 17, 0, 0, 0, 29, 0, 0, 0, 0, 0, 0, 0, 29, 0, 0, 0, 30, 0, 0, 0, 0, 0, 0, 0, 30, 0, 0, 0, 18, 0, 0, 0, 0, 0, 0, 0, 18, 0, 0, 0, 8, 0, 0, 0, 0, 0, 0, 0, 8, 0, 0, 0, 3, 0, 0, 0, 0, 0, 0, 0, 3, 0, 0, 0, 11, 0, 0, 0, 0, 0, 0, 0, 11, 0, 0, 0, 22, 0, 0, 0, 0, 0, 0, 0, 22, 0, 0, 0, 33, 0, 0, 0, 0, 0, 0, 0, 33, 0, 0, 0, 24, 0, 0, 0, 0, 0, 0, 0, 24, 0, 0, 0, 12, 0, 0, 0, 0, 0, 0, 0, 12, 0, 0, 0, 4, 0, 0, 0, 0, 0, 0, 0, 4, 0, 0, 0, 1, 0, 0, 0, 1, 0, 0, 0, 4, 0, 0, 0, 5, 0, 0, 0, 1, 0, 0, 0, 5, 0, 0, 0, 6, 0, 0, 0, 1, 0, 0, 0, 6, 0, 0, 0, 2, 0, 0, 0, 2, 0, 0, 0, 6, 0, 0, 0, 7, 0, 0, 0, 3, 0, 0, 0, 8, 0, 0, 0, 9, 0, 0, 0, 3, 0, 0, 0, 9, 0, 0, 0, 10, 0, 0, 0, 3, 0, 0, 0, 10, 0, 0, 0, 11, 0, 0, 0, 4, 0, 0, 0, 12, 0, 0, 0, 13, 0, 0, 0, 4, 0, 0, 0, 13, 0, 0, 0, 5, 0, 0, 0, 5, 0, 0, 0, 13, 0, 0, 0, 14, 0, 0, 0, 5, 0, 0, 0, 14, 0, 0, 0, 15, 0, 0, 0, 5, 0, 0, 0, 15, 0, 0, 0, 16, 0, 0, 0, 5, 0, 0, 0, 16, 0, 0, 0, 6, 0, 0, 0, 6, 0, 0, 0, 16, 0, 0, 0, 7, 0, 0, 0, 7, 0, 0, 0, 16, 0, 0, 0, 17, 0, 0, 0, 8, 0, 0, 0, 18, 0, 0, 0, 19, 0, 0, 0, 8, 0, 0, 0, 19, 0, 0, 0, 9, 0, 0, 0, 9, 0, 0, 0, 19, 0, 0, 0, 20, 0, 0, 0, 9, 0, 0, 0, 20, 0, 0, 0, 21, 0, 0, 0, 9, 0, 0, 0, 21, 0, 0, 0, 10, 0, 0, 0, 10, 0, 0, 0, 21, 0, 0, 0, 22, 0, 0, 0, 10, 0, 0, 0, 22, 0, 0, 0, 11, 0, 0, 0, 12, 0, 0, 0, 23, 0, 0, 0, 13, 0, 0, 0, 12, 0, 0, 0, 24, 0, 0, 0, 23, 0, 0, 0, 13, 0, 0, 0, 23, 0, 0, 0, 24, 0, 0, 0, 13, 0, 0, 0, 24, 0, 0, 0, 34, 0, 0, 0, 13, 0, 0, 0, 34, 0, 0, 0, 32, 0, 0, 0, 13, 0, 0, 0, 32, 0, 0, 0, 35, 0, 0, 0, 13, 0, 0, 0, 35, 0, 0, 0, 26, 0, 0, 0, 13, 0, 0, 0, 26, 0, 0, 0, 25, 0, 0, 0, 13, 0, 0, 0, 25, 0, 0, 0, 14, 0, 0, 0, 14, 0, 0, 0, 25, 0, 0, 0, 15, 0, 0, 0, 15, 0, 0, 0, 25, 0, 0, 0, 26, 0, 0, 0, 15, 0, 0, 0, 26, 0, 0, 0, 27, 0, 0, 0, 15, 0, 0, 0, 27, 0, 0, 0, 16, 0, 0, 0, 16, 0, 0, 0, 27, 0, 0, 0, 28, 0, 0, 0, 16, 0, 0, 0, 28, 0, 0, 0, 29, 0, 0, 0, 16, 0, 0, 0, 29, 0, 0, 0, 17, 0, 0, 0, 18, 0, 0, 0, 30, 0, 0, 0, 19, 0, 0, 0, 19, 0, 0, 0, 31, 0, 0, 0, 20, 0, 0, 0, 19, 0, 0, 0, 30, 0, 0, 0, 29, 0, 0, 0, 19, 0, 0, 0, 29, 0, 0, 0, 28, 0, 0, 0, 19, 0, 0, 0, 28, 0, 0, 0, 27, 0, 0, 0, 19, 0, 0, 0, 27, 0, 0, 0, 31, 0, 0, 0, 20, 0, 0, 0, 32, 0, 0, 0, 21, 0, 0, 0, 20, 0, 0, 0, 31, 0, 0, 0, 32, 0, 0, 0, 21, 0, 0, 0, 33, 0, 0, 0, 22, 0, 0, 0, 21, 0, 0, 0, 32, 0, 0, 0, 34, 0, 0, 0, 21, 0, 0, 0, 34, 0, 0, 0, 24, 0, 0, 0, 21, 0, 0, 0, 24, 0, 0, 0, 33, 0, 0, 0, 26, 0, 0, 0, 35, 0, 0, 0, 31, 0, 0, 0, 26, 0, 0, 0, 31, 0, 0, 0, 27, 0, 0, 0, 31, 0, 0, 0, 35, 0, 0, 0, 32, 0, 0, 0, 16, 0, 0, 0, 0, 0, 0, 0, 0, 0, 0, 0, 0, 0, 0, 0, 0, 0, 0, 0, 16, 0, 0, 0, 0, 0, 0, 0, 0, 0, 0, 0, 0, 0, 0, 0, 0, 0, 128, 63, 120, 0, 0, 0, 4, 0, 0, 0, 128, 40, 213, 185, 192, 189, 105, 62, 178, 159, 216, 188, 0, 128, 129, 57, 192, 189, 105, 62, 83, 58, 215, 188, 54, 186, 90, 188, 192, 189, 105, 62, 14, 198, 187, 188, 0, 168, 57, 184, 131, 161, 157, 62, 148, 254, 127, 189, 0, 128, 129, 57, 131, 161, 157, 62, 32, 180, 127, 189, 0, 128, 129, 57, 192, 189, 105, 62, 208, 126, 204, 60, 148, 210, 186, 188, 192, 189, 105, 62, 70, 110, 91, 188, 93, 136, 90, 189, 231, 165, 157, 62, 97, 186, 0, 189, 184, 119, 252, 188, 250, 162, 157, 62, 146, 128, 93, 189, 0, 28, 197, 184, 202, 41, 172, 62, 194, 77, 150, 189, 0, 128, 129, 57, 203, 0, 172, 62, 21, 222, 149, 189, 0, 128, 129, 57, 140, 180, 157, 62, 88, 74, 121, 61, 0, 101, 67, 185, 192, 189, 105, 62, 15, 109, 205, 60, 153, 208, 214, 188, 192, 189, 105, 62, 62, 141, 32, 186, 237, 142, 128, 189, 165, 47, 172, 62, 215, 197, 22, 189, 27, 171, 20, 189, 183, 44, 172, 62, 2, 1, 130, 189, 172, 202, 123, 189, 195, 171, 157, 62, 77, 169, 17, 186, 112, 32, 148, 189, 128, 53, 172, 62, 80, 240, 13, 186, 0, 128, 129, 57, 202, 41, 172, 62, 164, 25, 150, 189, 70, 101, 12, 188, 166, 74, 175, 62, 5, 68, 143, 189, 0, 28, 197, 184, 166, 74, 175, 62, 36, 250, 147, 189, 0, 128, 129, 57, 203, 68, 175, 62, 235, 212, 147, 189, 0, 128, 129, 57, 248, 203, 157, 62, 203, 148, 121, 61, 112, 160, 248, 188, 21, 179, 157, 62, 208, 34, 88, 61, 224, 123, 31, 188, 192, 189, 105, 62, 220, 213, 184, 60, 26, 243, 185, 188, 192, 189, 105, 62, 190, 211, 71, 60, 191, 116, 89, 189, 39, 176, 157, 62, 45, 90, 248, 60, 44, 34, 131, 189, 166, 74, 175, 62, 255, 35, 228, 188, 84, 33, 125, 189, 166, 74, 175, 62, 2, 144, 20, 189, 160, 94, 18, 189, 166, 74, 175, 62, 188, 6, 128, 189, 175, 215, 145, 189, 166, 74, 175, 62, 77, 169, 17, 186, 24, 214, 127, 189, 92, 59, 172, 62, 85, 86, 18, 61, 208, 159, 130, 189, 166, 74, 175, 62, 225, 217, 219, 60, 0, 128, 129, 57, 166, 74, 175, 62, 62, 130, 144, 61, 0, 128, 129, 57, 192, 63, 172, 62, 106, 206, 146, 61, 108, 124, 18, 189, 73, 62, 172, 62, 94, 149, 126, 61, 130, 179, 87, 188, 192, 189, 105, 62, 227, 99, 177, 60, 75, 70, 16, 189, 166, 74, 175, 62, 182, 175, 122, 61, 119, 232, 123, 189, 166, 74, 175, 62, 183, 2, 16, 61, 200, 201, 253, 187, 166, 74, 175, 62, 91, 52, 140, 61, 228, 0, 0, 0, 0, 0, 0, 0, 1, 0, 0, 0, 5, 0, 0, 0, 0, 0, 0, 0, 5, 0, 0, 0, 12, 0, 0, 0, 0, 0, 0, 0, 12, 0, 0, 0, 24, 0, 0, 0, 0, 0, 0, 0, 24, 0, 0, 0, 36, 0, 0, 0, 0, 0, 0, 0, 36, 0, 0, 0, 25, 0, 0, 0, 0, 0, 0, 0, 25, 0, 0, 0, 13, 0, 0, 0, 0, 0, 0, 0, 13, 0, 0, 0, 6, 0, 0, 0, 0, 0, 0, 0, 6, 0, 0, 0, 2, 0, 0, 0, 0, 0, 0, 0, 2, 0, 0, 0, 3, 0, 0, 0, 0, 0, 0, 0, 3, 0, 0, 0, 4, 0, 0, 0, 0, 0, 0, 0, 4, 0, 0, 0, 1, 0, 0, 0, 1, 0, 0, 0, 4, 0, 0, 0, 10, 0, 0, 0, 1, 0, 0, 0, 10, 0, 0, 0, 18, 0, 0, 0, 1, 0, 0, 0, 18, 0, 0, 0, 21, 0, 0, 0, 1, 0, 0, 0, 21, 0, 0, 0, 33, 0, 0, 0, 1, 0, 0, 0, 33, 0, 0, 0, 34, 0, 0, 0, 1, 0, 0, 0, 34, 0, 0, 0, 22, 0, 0, 0, 1, 0, 0, 0, 22, 0, 0, 0, 11, 0, 0, 0, 1, 0, 0, 0, 11, 0, 0, 0, 5, 0, 0, 0, 2, 0, 0, 0, 6, 0, 0, 0, 7, 0, 0, 0, 2, 0, 0, 0, 7, 0, 0, 0, 8, 0, 0, 0, 2, 0, 0, 0, 8, 0, 0, 0, 3, 0, 0, 0, 3, 0, 0, 0, 9, 0, 0, 0, 4, 0, 0, 0, 3, 0, 0, 0, 8, 0, 0, 0, 9, 0, 0, 0, 4, 0, 0, 0, 9, 0, 0, 0, 10, 0, 0, 0, 5, 0, 0, 0, 11, 0, 0, 0, 12, 0, 0, 0, 6, 0, 0, 0, 13, 0, 0, 0, 7, 0, 0, 0, 7, 0, 0, 0, 14, 0, 0, 0, 15, 0, 0, 0, 7, 0, 0, 0, 15, 0, 0, 0, 8, 0, 0, 0, 7, 0, 0, 0, 13, 0, 0, 0, 16, 0, 0, 0, 7, 0, 0, 0, 16, 0, 0, 0, 17, 0, 0, 0, 7, 0, 0, 0, 17, 0, 0, 0, 14, 0, 0, 0, 8, 0, 0, 0, 15, 0, 0, 0, 9, 0, 0, 0, 9, 0, 0, 0, 18, 0, 0, 0, 10, 0, 0, 0, 9, 0, 0, 0, 15, 0, 0, 0, 19, 0, 0, 0, 9, 0, 0, 0, 19, 0, 0, 0, 20, 0, 0, 0, 9, 0, 0, 0, 20, 0, 0, 0, 21, 0, 0, 0, 9, 0, 0, 0, 21, 0, 0, 0, 18, 0, 0, 0, 11, 0, 0, 0, 22, 0, 0, 0, 23, 0, 0, 0, 11, 0, 0, 0, 23, 0, 0, 0, 24, 0, 0, 0, 11, 0, 0, 0, 24, 0, 0, 0, 12, 0, 0, 0, 13, 0, 0, 0, 25, 0, 0, 0, 26, 0, 0, 0, 13, 0, 0, 0, 26, 0, 0, 0, 16, 0, 0, 0, 14, 0, 0, 0, 27, 0, 0, 0, 28, 0, 0, 0, 14, 0, 0, 0, 28, 0, 0, 0, 15, 0, 0, 0, 14, 0, 0, 0, 17, 0, 0, 0, 27, 0, 0, 0, 15, 0, 0, 0, 29, 0, 0, 0, 19, 0, 0, 0, 15, 0, 0, 0, 28, 0, 0, 0, 29, 0, 0, 0, 16, 0, 0, 0, 26, 0, 0, 0, 17, 0, 0, 0, 17, 0, 0, 0, 30, 0, 0, 0, 27, 0, 0, 0, 17, 0, 0, 0, 26, 0, 0, 0, 31, 0, 0, 0, 17, 0, 0, 0, 31, 0, 0, 0, 32, 0, 0, 0, 17, 0, 0, 0, 32, 0, 0, 0, 30, 0, 0, 0, 19, 0, 0, 0, 29, 0, 0, 0, 28, 0, 0, 0, 19, 0, 0, 0, 28, 0, 0, 0, 27, 0, 0, 0, 19, 0, 0, 0, 27, 0, 0, 0, 30, 0, 0, 0, 19, 0, 0, 0, 30, 0, 0, 0, 32, 0, 0, 0, 19, 0, 0, 0, 32, 0, 0, 0, 38, 0, 0, 0, 19, 0, 0, 0, 38, 0, 0, 0, 37, 0, 0, 0, 19, 0, 0, 0, 37, 0, 0, 0, 39, 0, 0, 0, 19, 0, 0, 0, 39, 0, 0, 0, 33, 0, 0, 0, 19, 0, 0, 0, 33, 0, 0, 0, 20, 0, 0, 0, 20, 0, 0, 0, 33, 0, 0, 0, 21, 0, 0, 0, 22, 0, 0, 0, 34, 0, 0, 0, 35, 0, 0, 0, 22, 0, 0, 0, 35, 0, 0, 0, 23, 0, 0, 0, 23, 0, 0, 0, 35, 0, 0, 0, 26, 0, 0, 0, 23, 0, 0, 0, 26, 0, 0, 0, 36, 0, 0, 0, 23, 0, 0, 0, 36, 0, 0, 0, 24, 0, 0, 0, 25, 0, 0, 0, 36, 0, 0, 0, 26, 0, 0, 0, 26, 0, 0, 0, 35, 0, 0, 0, 31, 0, 0, 0, 31, 0, 0, 0, 35, 0, 0, 0, 37, 0, 0, 0, 31, 0, 0, 0, 37, 0, 0, 0, 38, 0, 0, 0, 31, 0, 0, 0, 38, 0, 0, 0, 32, 0, 0, 0, 33, 0, 0, 0, 39, 0, 0, 0, 34, 0, 0, 0, 34, 0, 0, 0, 39, 0, 0, 0, 37, 0, 0, 0, 34, 0, 0, 0, 37, 0, 0, 0, 35, 0, 0, 0, 16, 0, 0, 0, 0, 0, 0, 0, 0, 0, 0, 0, 0, 0, 0, 0, 0, 0, 0, 0, 16, 0, 0, 0, 0, 0, 0, 0, 0, 0, 0, 0, 0, 0, 0, 0, 0, 0, 128, 63, 165, 0, 0, 0, 4, 0, 0, 0, 48, 11, 127, 184, 148, 77, 175, 62, 96, 254, 147, 189, 110, 233, 11, 188, 148, 77, 175, 62, 63, 68, 143, 189, 125, 71, 11, 189, 6, 182, 184, 62, 165, 48, 116, 189, 32, 92, 68, 184, 143, 180, 184, 62, 217, 0, 141, 189, 1, 76, 11, 61, 6, 182, 184, 62, 174, 100, 117, 189, 136, 88, 18, 61, 148, 77, 175, 62, 129, 160, 128, 189, 88, 69, 18, 189, 148, 77, 175, 62, 78, 254, 127, 189, 60, 139, 43, 189, 148, 77, 175, 62, 153, 141, 102, 189, 83, 9, 125, 189, 148, 77, 175, 62, 167, 128, 20, 189, 106, 212, 112, 189, 243, 184, 184, 62, 33, 175, 13, 189, 83, 181, 99, 188, 43, 186, 230, 62, 223, 0, 20, 188, 101, 131, 2, 188, 180, 184, 230, 62, 239, 24, 118, 188, 47, 165, 57, 57, 180, 184, 230, 62, 249, 68, 141, 188, 236, 197, 8, 60, 180, 184, 230, 62, 76, 62, 119, 188, 151, 226, 106, 60, 43, 186, 230, 62, 238, 16, 22, 188, 170, 195, 113, 61, 243, 184, 184, 62, 219, 205, 15, 189, 1, 120, 100, 61, 148, 77, 175, 62, 20, 228, 47, 189, 87, 26, 131, 189, 148, 77, 175, 62, 184, 4, 228, 188, 65, 222, 138, 189, 206, 190, 184, 62, 180, 37, 25, 186, 81, 129, 131, 188, 43, 186, 230, 62, 216, 39, 102, 186, 57, 41, 9, 188, 84, 125, 233, 62, 47, 244, 191, 187, 60, 148, 155, 187, 84, 125, 233, 62, 105, 86, 27, 188, 182, 252, 86, 57, 221, 123, 233, 62, 94, 204, 49, 188, 102, 121, 169, 59, 84, 125, 233, 62, 110, 6, 28, 188, 219, 203, 16, 60, 84, 125, 233, 62, 67, 180, 194, 187, 168, 170, 135, 60, 43, 186, 230, 62, 196, 105, 133, 186, 151, 232, 139, 61, 206, 190, 184, 62, 57, 234, 149, 186, 60, 219, 125, 61, 148, 77, 175, 62, 12, 174, 22, 189, 28, 220, 145, 189, 148, 77, 175, 62, 102, 37, 14, 186, 77, 150, 130, 189, 148, 77, 175, 62, 102, 210, 219, 60, 254, 174, 111, 189, 188, 193, 184, 62, 243, 229, 8, 61, 232, 143, 98, 188, 162, 187, 230, 62, 200, 119, 238, 59, 44, 121, 8, 188, 203, 126, 233, 62, 47, 10, 133, 59, 34, 64, 30, 188, 84, 125, 233, 62, 97, 125, 109, 186, 0, 128, 129, 57, 210, 186, 233, 62, 176, 125, 120, 186, 209, 146, 38, 60, 84, 125, 233, 62, 255, 190, 129, 186, 2, 8, 108, 60, 162, 187, 230, 62, 4, 205, 234, 59, 232, 123, 17, 60, 203, 126, 233, 62, 116, 191, 130, 59, 28, 223, 146, 61, 148, 77, 175, 62, 215, 20, 148, 186, 21, 233, 114, 61, 188, 193, 184, 62, 229, 213, 6, 61, 171, 44, 127, 61, 148, 77, 175, 62, 108, 211, 13, 61, 60, 213, 123, 189, 148, 77, 175, 62, 208, 0, 16, 61, 85, 55, 9, 189, 33, 198, 184, 62, 198, 124, 110, 61, 61, 115, 0, 188, 25, 189, 230, 62, 66, 105, 88, 60, 8, 212, 152, 187, 203, 126, 233, 62, 200, 98, 250, 59, 226, 213, 136, 57, 66, 128, 233, 62, 84, 247, 18, 60, 154, 57, 172, 59, 203, 126, 233, 62, 190, 2, 249, 59, 41, 92, 13, 61, 33, 198, 184, 62, 190, 72, 109, 61, 20, 214, 10, 60, 25, 189, 230, 62, 229, 67, 87, 60, 209, 106, 102, 61, 148, 77, 175, 62, 115, 221, 38, 61, 133, 38, 16, 189, 148, 77, 175, 62, 29, 177, 122, 61, 209, 26, 10, 58, 148, 77, 175, 62, 24, 175, 144, 61, 224, 111, 6, 58, 151, 199, 184, 62, 59, 148, 137, 61, 165, 129, 151, 57, 25, 189, 230, 62, 148, 239, 123, 60, 179, 148, 20, 61, 148, 77, 175, 62, 105, 110, 121, 61, 62, 1, 0, 0, 0, 0, 0, 0, 1, 0, 0, 0, 2, 0, 0, 0, 0, 0, 0, 0, 2, 0, 0, 0, 3, 0, 0, 0, 0, 0, 0, 0, 3, 0, 0, 0, 4, 0, 0, 0, 0, 0, 0, 0, 4, 0, 0, 0, 5, 0, 0, 0, 0, 0, 0, 0, 5, 0, 0, 0, 16, 0, 0, 0, 0, 0, 0, 0, 16, 0, 0, 0, 27, 0, 0, 0, 0, 0, 0, 0, 27, 0, 0, 0, 38, 0, 0, 0, 0, 0, 0, 0, 38, 0, 0, 0, 40, 0, 0, 0, 0, 0, 0, 0, 40, 0, 0, 0, 49, 0, 0, 0, 0, 0, 0, 0, 49, 0, 0, 0, 54, 0, 0, 0, 0, 0, 0, 0, 54, 0, 0, 0, 51, 0, 0, 0, 0, 0, 0, 0, 51, 0, 0, 0, 50, 0, 0, 0, 0, 0, 0, 0, 50, 0, 0, 0, 41, 0, 0, 0, 0, 0, 0, 0, 41, 0, 0, 0, 29, 0, 0, 0, 0, 0, 0, 0, 29, 0, 0, 0, 28, 0, 0, 0, 0, 0, 0, 0, 28, 0, 0, 0, 17, 0, 0, 0, 0, 0, 0, 0, 17, 0, 0, 0, 8, 0, 0, 0, 0, 0, 0, 0, 8, 0, 0, 0, 7, 0, 0, 0, 0, 0, 0, 0, 7, 0, 0, 0, 6, 0, 0, 0, 0, 0, 0, 0, 6, 0, 0, 0, 1, 0, 0, 0, 1, 0, 0, 0, 6, 0, 0, 0, 2, 0, 0, 0, 2, 0, 0, 0, 6, 0, 0, 0, 7, 0, 0, 0, 2, 0, 0, 0, 7, 0, 0, 0, 8, 0, 0, 0, 2, 0, 0, 0, 8, 0, 0, 0, 9, 0, 0, 0, 2, 0, 0, 0, 9, 0, 0, 0, 10, 0, 0, 0, 2, 0, 0, 0, 10, 0, 0, 0, 11, 0, 0, 0, 2, 0, 0, 0, 11, 0, 0, 0, 12, 0, 0, 0, 2, 0, 0, 0, 12, 0, 0, 0, 3, 0, 0, 0, 3, 0, 0, 0, 12, 0, 0, 0, 4, 0, 0, 0, 4, 0, 0, 0, 13, 0, 0, 0, 14, 0, 0, 0, 4, 0, 0, 0, 14, 0, 0, 0, 15, 0, 0, 0, 4, 0, 0, 0, 15, 0, 0, 0, 16, 0, 0, 0, 4, 0, 0, 0, 16, 0, 0, 0, 5, 0, 0, 0, 4, 0, 0, 0, 12, 0, 0, 0, 13, 0, 0, 0, 8, 0, 0, 0, 17, 0, 0, 0, 9, 0, 0, 0, 9, 0, 0, 0, 17, 0, 0, 0, 18, 0, 0, 0, 9, 0, 0, 0, 18, 0, 0, 0, 10, 0, 0, 0, 10, 0, 0, 0, 19, 0, 0, 0, 20, 0, 0, 0, 10, 0, 0, 0, 20, 0, 0, 0, 11, 0, 0, 0, 10, 0, 0, 0, 18, 0, 0, 0, 19, 0, 0, 0, 11, 0, 0, 0, 20, 0, 0, 0, 21, 0, 0, 0, 11, 0, 0, 0, 21, 0, 0, 0, 22, 0, 0, 0, 11, 0, 0, 0, 22, 0, 0, 0, 12, 0, 0, 0, 12, 0, 0, 0, 22, 0, 0, 0, 13, 0, 0, 0, 13, 0, 0, 0, 22, 0, 0, 0, 23, 0, 0, 0, 13, 0, 0, 0, 23, 0, 0, 0, 24, 0, 0, 0, 13, 0, 0, 0, 24, 0, 0, 0, 14, 0, 0, 0, 14, 0, 0, 0, 24, 0, 0, 0, 25, 0, 0, 0, 14, 0, 0, 0, 25, 0, 0, 0, 26, 0, 0, 0, 14, 0, 0, 0, 26, 0, 0, 0, 15, 0, 0, 0, 15, 0, 0, 0, 26, 0, 0, 0, 27, 0, 0, 0, 15, 0, 0, 0, 27, 0, 0, 0, 16, 0, 0, 0, 17, 0, 0, 0, 28, 0, 0, 0, 18, 0, 0, 0, 18, 0, 0, 0, 28, 0, 0, 0, 29, 0, 0, 0, 18, 0, 0, 0, 29, 0, 0, 0, 30, 0, 0, 0, 18, 0, 0, 0, 30, 0, 0, 0, 31, 0, 0, 0, 18, 0, 0, 0, 31, 0, 0, 0, 19, 0, 0, 0, 19, 0, 0, 0, 31, 0, 0, 0, 32, 0, 0, 0, 19, 0, 0, 0, 32, 0, 0, 0, 33, 0, 0, 0, 19, 0, 0, 0, 33, 0, 0, 0, 20, 0, 0, 0, 20, 0, 0, 0, 33, 0, 0, 0, 34, 0, 0, 0, 20, 0, 0, 0, 34, 0, 0, 0, 21, 0, 0, 0, 21, 0, 0, 0, 34, 0, 0, 0, 22, 0, 0, 0, 22, 0, 0, 0, 34, 0, 0, 0, 23, 0, 0, 0, 23, 0, 0, 0, 34, 0, 0, 0, 24, 0, 0, 0, 24, 0, 0, 0, 35, 0, 0, 0, 25, 0, 0, 0, 24, 0, 0, 0, 34, 0, 0, 0, 35, 0, 0, 0, 25, 0, 0, 0, 36, 0, 0, 0, 26, 0, 0, 0, 25, 0, 0, 0, 35, 0, 0, 0, 37, 0, 0, 0, 25, 0, 0, 0, 37, 0, 0, 0, 36, 0, 0, 0, 26, 0, 0, 0, 38, 0, 0, 0, 27, 0, 0, 0, 26, 0, 0, 0, 36, 0, 0, 0, 39, 0, 0, 0, 26, 0, 0, 0, 39, 0, 0, 0, 40, 0, 0, 0, 26, 0, 0, 0, 40, 0, 0, 0, 38, 0, 0, 0, 29, 0, 0, 0, 41, 0, 0, 0, 30, 0, 0, 0, 30, 0, 0, 0, 42, 0, 0, 0, 31, 0, 0, 0, 30, 0, 0, 0, 41, 0, 0, 0, 42, 0, 0, 0, 31, 0, 0, 0, 43, 0, 0, 0, 32, 0, 0, 0, 31, 0, 0, 0, 42, 0, 0, 0, 43, 0, 0, 0, 32, 0, 0, 0, 43, 0, 0, 0, 44, 0, 0, 0, 32, 0, 0, 0, 44, 0, 0, 0, 34, 0, 0, 0, 32, 0, 0, 0, 34, 0, 0, 0, 33, 0, 0, 0, 34, 0, 0, 0, 45, 0, 0, 0, 46, 0, 0, 0, 34, 0, 0, 0, 46, 0, 0, 0, 37, 0, 0, 0, 34, 0, 0, 0, 37, 0, 0, 0, 35, 0, 0, 0, 34, 0, 0, 0, 44, 0, 0, 0, 45, 0, 0, 0, 36, 0, 0, 0, 47, 0, 0, 0, 39, 0, 0, 0, 36, 0, 0, 0, 37, 0, 0, 0, 48, 0, 0, 0, 36, 0, 0, 0, 48, 0, 0, 0, 47, 0, 0, 0, 37, 0, 0, 0, 46, 0, 0, 0, 48, 0, 0, 0, 39, 0, 0, 0, 49, 0, 0, 0, 40, 0, 0, 0, 39, 0, 0, 0, 47, 0, 0, 0, 49, 0, 0, 0, 41, 0, 0, 0, 50, 0, 0, 0, 42, 0, 0, 0, 42, 0, 0, 0, 50, 0, 0, 0, 51, 0, 0, 0, 42, 0, 0, 0, 51, 0, 0, 0, 52, 0, 0, 0, 42, 0, 0, 0, 52, 0, 0, 0, 53, 0, 0, 0, 42, 0, 0, 0, 53, 0, 0, 0, 43, 0, 0, 0, 43, 0, 0, 0, 53, 0, 0, 0, 45, 0, 0, 0, 43, 0, 0, 0, 45, 0, 0, 0, 44, 0, 0, 0, 45, 0, 0, 0, 53, 0, 0, 0, 48, 0, 0, 0, 45, 0, 0, 0, 48, 0, 0, 0, 46, 0, 0, 0, 47, 0, 0, 0, 48, 0, 0, 0, 53, 0, 0, 0, 47, 0, 0, 0, 53, 0, 0, 0, 52, 0, 0, 0, 47, 0, 0, 0, 52, 0, 0, 0, 51, 0, 0, 0, 47, 0, 0, 0, 51, 0, 0, 0, 54, 0, 0, 0, 47, 0, 0, 0, 54, 0, 0, 0, 49, 0, 0, 0, 16, 0, 0, 0, 0, 0, 0, 0, 0, 0, 0, 0, 0, 0, 0, 0, 0, 0, 0, 0, 16, 0, 0, 0, 0, 0, 0, 0, 0, 0, 0, 0, 0, 0, 0, 0, 0, 0, 128, 63, 243, 0, 0, 0, 4, 0, 0, 0, 199, 116, 180, 184, 63, 103, 20, 62, 99, 41, 162, 189, 199, 116, 180, 184, 253, 51, 26, 62, 43, 43, 159, 189, 152, 205, 29, 61, 253, 51, 26, 62, 10, 104, 138, 189, 170, 166, 32, 61, 26, 109, 20, 62, 54, 229, 140, 189, 170, 166, 32, 61, 54, 156, 15, 62, 37, 221, 140, 189, 199, 116, 180, 184, 72, 153, 15, 62, 82, 33, 162, 189, 29, 10, 33, 189, 54, 156, 15, 62, 181, 43, 140, 189, 29, 10, 33, 189, 26, 109, 20, 62, 197, 51, 140, 189, 215, 32, 30, 189, 253, 51, 26, 62, 171, 190, 137, 189, 80, 33, 207, 185, 211, 186, 105, 62, 45, 164, 216, 188, 242, 105, 77, 60, 211, 186, 105, 62, 15, 170, 188, 188, 223, 255, 136, 61, 198, 60, 26, 62, 210, 160, 33, 189, 10, 144, 139, 61, 228, 117, 20, 62, 215, 134, 36, 189, 188, 119, 139, 61, 255, 164, 15, 62, 181, 118, 36, 189, 238, 101, 27, 61, 208, 131, 11, 62, 84, 35, 136, 189, 168, 76, 103, 184, 226, 128, 11, 62, 16, 182, 156, 189, 186, 104, 134, 189, 153, 140, 11, 62, 189, 198, 28, 189, 191, 31, 139, 189, 255, 164, 15, 62, 188, 17, 34, 189, 95, 120, 27, 189, 208, 131, 11, 62, 244, 121, 135, 189, 191, 31, 139, 189, 228, 117, 20, 62, 222, 33, 34, 189, 200, 164, 186, 188, 211, 186, 105, 62, 218, 75, 91, 188, 213, 156, 90, 188, 211, 186, 105, 62, 247, 167, 187, 188, 0, 41, 34, 188, 211, 186, 105, 62, 50, 120, 195, 188, 149, 143, 136, 189, 198, 60, 26, 62, 250, 75, 31, 189, 91, 173, 180, 60, 211, 186, 105, 62, 169, 146, 94, 188, 133, 140, 158, 61, 125, 72, 26, 62, 43, 77, 122, 186, 127, 234, 209, 60, 211, 186, 105, 62, 39, 10, 90, 186, 178, 109, 161, 61, 154, 129, 20, 62, 43, 77, 122, 186, 178, 109, 161, 61, 200, 173, 15, 62, 43, 77, 122, 186, 183, 192, 134, 61, 153, 140, 11, 62, 149, 27, 31, 189, 177, 130, 217, 60, 210, 186, 233, 61, 107, 205, 62, 189, 95, 127, 60, 61, 210, 186, 233, 61, 12, 82, 223, 188, 86, 249, 21, 60, 210, 186, 233, 61, 109, 148, 81, 189, 8, 138, 29, 56, 210, 186, 233, 61, 216, 104, 91, 189, 88, 164, 216, 188, 210, 186, 233, 61, 117, 219, 61, 189, 23, 23, 32, 189, 210, 186, 233, 61, 210, 142, 9, 189, 148, 61, 59, 189, 210, 186, 233, 61, 62, 11, 220, 188, 129, 200, 87, 189, 210, 186, 233, 61, 178, 29, 194, 185, 242, 225, 154, 189, 98, 149, 11, 62, 174, 218, 161, 185, 47, 75, 160, 189, 200, 173, 15, 62, 237, 201, 153, 185, 32, 216, 161, 189, 8, 112, 20, 62, 208, 202, 82, 185, 166, 222, 158, 189, 143, 110, 26, 62, 174, 218, 161, 185, 76, 190, 214, 188, 211, 186, 105, 62, 128, 140, 29, 186, 65, 66, 140, 61, 81, 141, 20, 62, 88, 37, 29, 61, 23, 178, 137, 61, 34, 87, 26, 62, 116, 79, 26, 61, 148, 176, 181, 60, 211, 186, 105, 62, 2, 148, 68, 60, 244, 41, 140, 61, 108, 188, 15, 62, 122, 53, 29, 61, 213, 106, 135, 61, 25, 161, 11, 62, 123, 234, 23, 61, 91, 252, 155, 61, 98, 149, 11, 62, 202, 68, 118, 186, 235, 220, 89, 61, 210, 186, 233, 61, 102, 249, 81, 186, 39, 42, 58, 189, 210, 186, 233, 61, 202, 185, 213, 60, 156, 190, 133, 189, 25, 161, 11, 62, 83, 63, 26, 61, 161, 117, 138, 189, 108, 188, 15, 62, 115, 154, 31, 61, 161, 117, 138, 189, 81, 141, 20, 62, 81, 138, 31, 61, 119, 229, 135, 189, 34, 87, 26, 62, 76, 164, 28, 61, 93, 226, 185, 188, 211, 186, 105, 62, 208, 218, 71, 60, 13, 37, 32, 61, 15, 90, 26, 62, 104, 64, 135, 61, 83, 14, 35, 61, 26, 150, 20, 62, 131, 181, 137, 61, 83, 14, 35, 61, 72, 194, 15, 62, 147, 189, 137, 61, 18, 183, 121, 60, 211, 186, 105, 62, 96, 193, 155, 60, 48, 173, 29, 61, 226, 169, 11, 62, 211, 11, 133, 61, 151, 49, 61, 61, 210, 186, 233, 61, 252, 114, 210, 60, 71, 157, 9, 61, 210, 186, 233, 61, 122, 53, 29, 61, 64, 146, 30, 189, 210, 186, 233, 61, 213, 69, 6, 61, 14, 25, 213, 188, 210, 186, 233, 61, 196, 192, 57, 61, 233, 32, 25, 189, 226, 169, 11, 62, 51, 181, 133, 61, 116, 162, 30, 189, 72, 194, 15, 62, 4, 111, 138, 61, 116, 162, 30, 189, 26, 150, 20, 62, 243, 102, 138, 61, 97, 201, 27, 189, 15, 90, 26, 62, 200, 233, 135, 61, 163, 64, 165, 188, 211, 186, 105, 62, 39, 240, 112, 60, 110, 180, 80, 60, 211, 186, 105, 62, 78, 108, 176, 60, 15, 112, 59, 185, 211, 186, 105, 62, 131, 104, 205, 60, 34, 169, 27, 58, 234, 95, 26, 62, 232, 172, 156, 61, 9, 182, 31, 58, 26, 150, 20, 62, 32, 171, 159, 61, 9, 182, 31, 58, 35, 200, 15, 62, 49, 179, 159, 61, 34, 169, 27, 58, 190, 175, 11, 62, 222, 63, 154, 61, 144, 75, 220, 60, 210, 186, 233, 61, 206, 206, 56, 61, 160, 157, 254, 57, 210, 186, 233, 61, 238, 59, 86, 61, 82, 31, 31, 188, 211, 186, 105, 62, 216, 221, 184, 60, 40, 147, 87, 188, 211, 186, 105, 62, 102, 110, 177, 60, 243, 83, 30, 60, 210, 186, 233, 61, 186, 6, 76, 61, 218, 1, 0, 0, 0, 0, 0, 0, 1, 0, 0, 0, 2, 0, 0, 0, 0, 0, 0, 0, 2, 0, 0, 0, 3, 0, 0, 0, 0, 0, 0, 0, 3, 0, 0, 0, 4, 0, 0, 0, 0, 0, 0, 0, 4, 0, 0, 0, 5, 0, 0, 0, 0, 0, 0, 0, 5, 0, 0, 0, 6, 0, 0, 0, 0, 0, 0, 0, 6, 0, 0, 0, 7, 0, 0, 0, 0, 0, 0, 0, 7, 0, 0, 0, 8, 0, 0, 0, 0, 0, 0, 0, 8, 0, 0, 0, 1, 0, 0, 0, 1, 0, 0, 0, 8, 0, 0, 0, 9, 0, 0, 0, 1, 0, 0, 0, 9, 0, 0, 0, 2, 0, 0, 0, 2, 0, 0, 0, 10, 0, 0, 0, 11, 0, 0, 0, 2, 0, 0, 0, 11, 0, 0, 0, 12, 0, 0, 0, 2, 0, 0, 0, 12, 0, 0, 0, 3, 0, 0, 0, 2, 0, 0, 0, 9, 0, 0, 0, 10, 0, 0, 0, 3, 0, 0, 0, 12, 0, 0, 0, 4, 0, 0, 0, 4, 0, 0, 0, 12, 0, 0, 0, 13, 0, 0, 0, 4, 0, 0, 0, 13, 0, 0, 0, 14, 0, 0, 0, 4, 0, 0, 0, 14, 0, 0, 0, 15, 0, 0, 0, 4, 0, 0, 0, 15, 0, 0, 0, 5, 0, 0, 0, 5, 0, 0, 0, 15, 0, 0, 0, 6, 0, 0, 0, 6, 0, 0, 0, 16, 0, 0, 0, 17, 0, 0, 0, 6, 0, 0, 0, 17, 0, 0, 0, 19, 0, 0, 0, 6, 0, 0, 0, 19, 0, 0, 0, 7, 0, 0, 0, 6, 0, 0, 0, 15, 0, 0, 0, 18, 0, 0, 0, 6, 0, 0, 0, 18, 0, 0, 0, 16, 0, 0, 0, 7, 0, 0, 0, 19, 0, 0, 0, 8, 0, 0, 0, 8, 0, 0, 0, 20, 0, 0, 0, 21, 0, 0, 0, 8, 0, 0, 0, 21, 0, 0, 0, 22, 0, 0, 0, 8, 0, 0, 0, 22, 0, 0, 0, 9, 0, 0, 0, 8, 0, 0, 0, 19, 0, 0, 0, 23, 0, 0, 0, 8, 0, 0, 0, 23, 0, 0, 0, 20, 0, 0, 0, 9, 0, 0, 0, 22, 0, 0, 0, 21, 0, 0, 0, 9, 0, 0, 0, 21, 0, 0, 0, 20, 0, 0, 0, 9, 0, 0, 0, 20, 0, 0, 0, 42, 0, 0, 0, 9, 0, 0, 0, 42, 0, 0, 0, 55, 0, 0, 0, 9, 0, 0, 0, 55, 0, 0, 0, 69, 0, 0, 0, 9, 0, 0, 0, 69, 0, 0, 0, 79, 0, 0, 0, 9, 0, 0, 0, 79, 0, 0, 0, 78, 0, 0, 0, 9, 0, 0, 0, 78, 0, 0, 0, 71, 0, 0, 0, 9, 0, 0, 0, 71, 0, 0, 0, 70, 0, 0, 0, 9, 0, 0, 0, 70, 0, 0, 0, 59, 0, 0, 0, 9, 0, 0, 0, 59, 0, 0, 0, 45, 0, 0, 0, 9, 0, 0, 0, 45, 0, 0, 0, 26, 0, 0, 0, 9, 0, 0, 0, 26, 0, 0, 0, 24, 0, 0, 0, 9, 0, 0, 0, 24, 0, 0, 0, 10, 0, 0, 0, 10, 0, 0, 0, 24, 0, 0, 0, 11, 0, 0, 0, 11, 0, 0, 0, 25, 0, 0, 0, 12, 0, 0, 0, 11, 0, 0, 0, 24, 0, 0, 0, 26, 0, 0, 0, 11, 0, 0, 0, 26, 0, 0, 0, 25, 0, 0, 0, 12, 0, 0, 0, 25, 0, 0, 0, 27, 0, 0, 0, 12, 0, 0, 0, 27, 0, 0, 0, 28, 0, 0, 0, 12, 0, 0, 0, 28, 0, 0, 0, 13, 0, 0, 0, 13, 0, 0, 0, 28, 0, 0, 0, 29, 0, 0, 0, 13, 0, 0, 0, 29, 0, 0, 0, 14, 0, 0, 0, 14, 0, 0, 0, 30, 0, 0, 0, 15, 0, 0, 0, 14, 0, 0, 0, 29, 0, 0, 0, 31, 0, 0, 0, 14, 0, 0, 0, 31, 0, 0, 0, 30, 0, 0, 0, 15, 0, 0, 0, 30, 0, 0, 0, 32, 0, 0, 0, 15, 0, 0, 0, 32, 0, 0, 0, 33, 0, 0, 0, 15, 0, 0, 0, 33, 0, 0, 0, 34, 0, 0, 0, 15, 0, 0, 0, 34, 0, 0, 0, 18, 0, 0, 0, 16, 0, 0, 0, 18, 0, 0, 0, 34, 0, 0, 0, 16, 0, 0, 0, 34, 0, 0, 0, 35, 0, 0, 0, 16, 0, 0, 0, 35, 0, 0, 0, 36, 0, 0, 0, 16, 0, 0, 0, 36, 0, 0, 0, 37, 0, 0, 0, 16, 0, 0, 0, 37, 0, 0, 0, 38, 0, 0, 0, 16, 0, 0, 0, 38, 0, 0, 0, 17, 0, 0, 0, 17, 0, 0, 0, 38, 0, 0, 0, 39, 0, 0, 0, 17, 0, 0, 0, 39, 0, 0, 0, 40, 0, 0, 0, 17, 0, 0, 0, 40, 0, 0, 0, 19, 0, 0, 0, 19, 0, 0, 0, 40, 0, 0, 0, 41, 0, 0, 0, 19, 0, 0, 0, 41, 0, 0, 0, 23, 0, 0, 0, 20, 0, 0, 0, 23, 0, 0, 0, 41, 0, 0, 0, 20, 0, 0, 0, 41, 0, 0, 0, 42, 0, 0, 0, 25, 0, 0, 0, 43, 0, 0, 0, 27, 0, 0, 0, 25, 0, 0, 0, 26, 0, 0, 0, 44, 0, 0, 0, 25, 0, 0, 0, 44, 0, 0, 0, 43, 0, 0, 0, 26, 0, 0, 0, 45, 0, 0, 0, 44, 0, 0, 0, 27, 0, 0, 0, 43, 0, 0, 0, 28, 0, 0, 0, 28, 0, 0, 0, 43, 0, 0, 0, 46, 0, 0, 0, 28, 0, 0, 0, 46, 0, 0, 0, 47, 0, 0, 0, 28, 0, 0, 0, 47, 0, 0, 0, 48, 0, 0, 0, 28, 0, 0, 0, 48, 0, 0, 0, 29, 0, 0, 0, 29, 0, 0, 0, 48, 0, 0, 0, 31, 0, 0, 0, 30, 0, 0, 0, 31, 0, 0, 0, 49, 0, 0, 0, 30, 0, 0, 0, 49, 0, 0, 0, 61, 0, 0, 0, 30, 0, 0, 0, 61, 0, 0, 0, 62, 0, 0, 0, 30, 0, 0, 0, 62, 0, 0, 0, 76, 0, 0, 0, 30, 0, 0, 0, 76, 0, 0, 0, 80, 0, 0, 0, 30, 0, 0, 0, 80, 0, 0, 0, 77, 0, 0, 0, 30, 0, 0, 0, 77, 0, 0, 0, 64, 0, 0, 0, 30, 0, 0, 0, 64, 0, 0, 0, 63, 0, 0, 0, 30, 0, 0, 0, 63, 0, 0, 0, 50, 0, 0, 0, 30, 0, 0, 0, 50, 0, 0, 0, 37, 0, 0, 0, 30, 0, 0, 0, 37, 0, 0, 0, 36, 0, 0, 0, 30, 0, 0, 0, 36, 0, 0, 0, 35, 0, 0, 0, 30, 0, 0, 0, 35, 0, 0, 0, 34, 0, 0, 0, 30, 0, 0, 0, 34, 0, 0, 0, 33, 0, 0, 0, 30, 0, 0, 0, 33, 0, 0, 0, 32, 0, 0, 0, 31, 0, 0, 0, 48, 0, 0, 0, 49, 0, 0, 0, 37, 0, 0, 0, 50, 0, 0, 0, 51, 0, 0, 0, 37, 0, 0, 0, 51, 0, 0, 0, 38, 0, 0, 0, 38, 0, 0, 0, 51, 0, 0, 0, 52, 0, 0, 0, 38, 0, 0, 0, 52, 0, 0, 0, 39, 0, 0, 0, 39, 0, 0, 0, 52, 0, 0, 0, 40, 0, 0, 0, 40, 0, 0, 0, 52, 0, 0, 0, 53, 0, 0, 0, 40, 0, 0, 0, 53, 0, 0, 0, 41, 0, 0, 0, 41, 0, 0, 0, 53, 0, 0, 0, 54, 0, 0, 0, 41, 0, 0, 0, 54, 0, 0, 0, 55, 0, 0, 0, 41, 0, 0, 0, 55, 0, 0, 0, 42, 0, 0, 0, 43, 0, 0, 0, 44, 0, 0, 0, 56, 0, 0, 0, 43, 0, 0, 0, 56, 0, 0, 0, 57, 0, 0, 0, 43, 0, 0, 0, 57, 0, 0, 0, 58, 0, 0, 0, 43, 0, 0, 0, 58, 0, 0, 0, 46, 0, 0, 0, 44, 0, 0, 0, 45, 0, 0, 0, 59, 0, 0, 0, 44, 0, 0, 0, 59, 0, 0, 0, 56, 0, 0, 0, 46, 0, 0, 0, 58, 0, 0, 0, 60, 0, 0, 0, 46, 0, 0, 0, 60, 0, 0, 0, 47, 0, 0, 0, 47, 0, 0, 0, 61, 0, 0, 0, 48, 0, 0, 0, 47, 0, 0, 0, 60, 0, 0, 0, 62, 0, 0, 0, 47, 0, 0, 0, 62, 0, 0, 0, 61, 0, 0, 0, 48, 0, 0, 0, 61, 0, 0, 0, 49, 0, 0, 0, 50, 0, 0, 0, 63, 0, 0, 0, 51, 0, 0, 0, 51, 0, 0, 0, 63, 0, 0, 0, 64, 0, 0, 0, 51, 0, 0, 0, 64, 0, 0, 0, 65, 0, 0, 0, 51, 0, 0, 0, 65, 0, 0, 0, 66, 0, 0, 0, 51, 0, 0, 0, 66, 0, 0, 0, 52, 0, 0, 0, 52, 0, 0, 0, 66, 0, 0, 0, 67, 0, 0, 0, 52, 0, 0, 0, 67, 0, 0, 0, 53, 0, 0, 0, 53, 0, 0, 0, 67, 0, 0, 0, 68, 0, 0, 0, 53, 0, 0, 0, 68, 0, 0, 0, 54, 0, 0, 0, 54, 0, 0, 0, 68, 0, 0, 0, 69, 0, 0, 0, 54, 0, 0, 0, 69, 0, 0, 0, 55, 0, 0, 0, 56, 0, 0, 0, 59, 0, 0, 0, 70, 0, 0, 0, 56, 0, 0, 0, 70, 0, 0, 0, 71, 0, 0, 0, 56, 0, 0, 0, 71, 0, 0, 0, 72, 0, 0, 0, 56, 0, 0, 0, 72, 0, 0, 0, 73, 0, 0, 0, 56, 0, 0, 0, 73, 0, 0, 0, 57, 0, 0, 0, 57, 0, 0, 0, 73, 0, 0, 0, 74, 0, 0, 0, 57, 0, 0, 0, 74, 0, 0, 0, 58, 0, 0, 0, 58, 0, 0, 0, 74, 0, 0, 0, 60, 0, 0, 0, 60, 0, 0, 0, 74, 0, 0, 0, 75, 0, 0, 0, 60, 0, 0, 0, 75, 0, 0, 0, 76, 0, 0, 0, 60, 0, 0, 0, 76, 0, 0, 0, 62, 0, 0, 0, 64, 0, 0, 0, 77, 0, 0, 0, 75, 0, 0, 0, 64, 0, 0, 0, 75, 0, 0, 0, 65, 0, 0, 0, 65, 0, 0, 0, 75, 0, 0, 0, 66, 0, 0, 0, 66, 0, 0, 0, 75, 0, 0, 0, 74, 0, 0, 0, 66, 0, 0, 0, 74, 0, 0, 0, 67, 0, 0, 0, 67, 0, 0, 0, 74, 0, 0, 0, 73, 0, 0, 0, 67, 0, 0, 0, 73, 0, 0, 0, 68, 0, 0, 0, 68, 0, 0, 0, 71, 0, 0, 0, 78, 0, 0, 0, 68, 0, 0, 0, 78, 0, 0, 0, 79, 0, 0, 0, 68, 0, 0, 0, 79, 0, 0, 0, 69, 0, 0, 0, 68, 0, 0, 0, 73, 0, 0, 0, 72, 0, 0, 0, 68, 0, 0, 0, 72, 0, 0, 0, 71, 0, 0, 0, 75, 0, 0, 0, 77, 0, 0, 0, 80, 0, 0, 0, 75, 0, 0, 0, 80, 0, 0, 0, 76, 0, 0, 0, 16, 0, 0, 0, 0, 0, 0, 0, 0, 0, 0, 0, 0, 0, 0, 0, 0, 0, 0, 0, 16, 0, 0, 0, 0, 0, 0, 0, 0, 0, 0, 0, 0, 0, 0, 0, 0, 0, 128, 63, 129, 0, 0, 0, 4, 0, 0, 0, 98, 59, 166, 61, 0, 0, 0, 0, 26, 49, 217, 189, 131, 217, 80, 61, 94, 14, 180, 61, 139, 139, 156, 189, 32, 104, 168, 61, 21, 26, 180, 61, 58, 235, 122, 189, 30, 242, 211, 61, 0, 0, 0, 0, 78, 22, 190, 189, 160, 124, 76, 185, 0, 0, 0, 0, 202, 120, 216, 189, 157, 69, 217, 60, 211, 186, 233, 61, 198, 199, 62, 189, 80, 242, 173, 189, 0, 0, 0, 0, 243, 159, 215, 189, 127, 172, 105, 189, 94, 14, 180, 61, 249, 91, 155, 189, 192, 255, 122, 56, 211, 186, 233, 61, 224, 104, 91, 189, 191, 237, 168, 61, 57, 61, 180, 61, 56, 133, 112, 186, 141, 96, 203, 61, 108, 167, 25, 61, 27, 2, 151, 61, 129, 18, 202, 61, 0, 236, 24, 61, 48, 196, 154, 189, 40, 121, 226, 61, 0, 0, 0, 0, 162, 123, 178, 189, 33, 104, 60, 61, 211, 186, 233, 61, 83, 86, 223, 188, 5, 185, 89, 61, 211, 186, 233, 61, 108, 106, 85, 186, 7, 210, 184, 189, 0, 0, 0, 0, 44, 81, 204, 189, 115, 229, 156, 189, 21, 26, 180, 61, 136, 59, 106, 189, 178, 163, 216, 188, 211, 186, 233, 61, 64, 217, 61, 189, 93, 115, 169, 61, 94, 96, 180, 61, 191, 124, 115, 61, 72, 32, 228, 61, 0, 0, 0, 0, 60, 207, 174, 61, 74, 26, 61, 61, 211, 186, 233, 61, 104, 86, 210, 60, 100, 57, 216, 189, 0, 0, 0, 0, 215, 150, 169, 189, 89, 229, 155, 189, 130, 90, 180, 61, 45, 100, 104, 61, 240, 192, 87, 189, 211, 186, 233, 61, 123, 254, 209, 185, 121, 56, 59, 189, 211, 186, 233, 61, 88, 30, 220, 188, 83, 20, 32, 189, 211, 186, 233, 61, 99, 150, 9, 189, 213, 212, 142, 61, 108, 167, 25, 61, 82, 164, 187, 61, 150, 59, 168, 61, 0, 0, 0, 0, 206, 6, 214, 61, 96, 164, 213, 61, 0, 0, 0, 0, 30, 160, 186, 61, 90, 132, 9, 61, 211, 186, 233, 61, 86, 23, 29, 61, 62, 14, 220, 60, 211, 186, 233, 61, 60, 180, 56, 61, 154, 117, 83, 61, 57, 102, 180, 61, 64, 97, 153, 61, 54, 224, 214, 189, 0, 0, 0, 0, 54, 186, 169, 61, 44, 65, 183, 189, 0, 0, 0, 0, 126, 51, 204, 61, 14, 64, 172, 189, 0, 0, 0, 0, 110, 119, 215, 61, 35, 250, 102, 189, 57, 102, 180, 61, 143, 25, 154, 61, 94, 252, 212, 188, 211, 186, 233, 61, 193, 162, 57, 61, 120, 131, 30, 189, 211, 186, 233, 61, 11, 35, 6, 61, 247, 22, 58, 189, 211, 186, 233, 61, 100, 142, 213, 60, 28, 125, 77, 189, 211, 186, 233, 61, 161, 135, 15, 60, 100, 240, 86, 61, 0, 0, 0, 0, 138, 93, 214, 61, 120, 154, 4, 58, 211, 186, 233, 61, 44, 46, 86, 61, 208, 181, 54, 58, 0, 0, 0, 0, 245, 201, 214, 61, 246, 0, 0, 0, 0, 0, 0, 0, 1, 0, 0, 0, 2, 0, 0, 0, 0, 0, 0, 0, 2, 0, 0, 0, 3, 0, 0, 0, 0, 0, 0, 0, 3, 0, 0, 0, 12, 0, 0, 0, 0, 0, 0, 0, 12, 0, 0, 0, 19, 0, 0, 0, 0, 0, 0, 0, 19, 0, 0, 0, 28, 0, 0, 0, 0, 0, 0, 0, 28, 0, 0, 0, 27, 0, 0, 0, 0, 0, 0, 0, 27, 0, 0, 0, 40, 0, 0, 0, 0, 0, 0, 0, 40, 0, 0, 0, 42, 0, 0, 0, 0, 0, 0, 0, 42, 0, 0, 0, 34, 0, 0, 0, 0, 0, 0, 0, 34, 0, 0, 0, 33, 0, 0, 0, 0, 0, 0, 0, 33, 0, 0, 0, 32, 0, 0, 0, 0, 0, 0, 0, 32, 0, 0, 0, 21, 0, 0, 0, 0, 0, 0, 0, 21, 0, 0, 0, 15, 0, 0, 0, 0, 0, 0, 0, 15, 0, 0, 0, 6, 0, 0, 0, 0, 0, 0, 0, 6, 0, 0, 0, 4, 0, 0, 0, 0, 0, 0, 0, 4, 0, 0, 0, 1, 0, 0, 0, 1, 0, 0, 0, 5, 0, 0, 0, 2, 0, 0, 0, 1, 0, 0, 0, 4, 0, 0, 0, 6, 0, 0, 0, 1, 0, 0, 0, 6, 0, 0, 0, 7, 0, 0, 0, 1, 0, 0, 0, 7, 0, 0, 0, 8, 0, 0, 0, 1, 0, 0, 0, 8, 0, 0, 0, 5, 0, 0, 0, 2, 0, 0, 0, 9, 0, 0, 0, 10, 0, 0, 0, 2, 0, 0, 0, 10, 0, 0, 0, 11, 0, 0, 0, 2, 0, 0, 0, 11, 0, 0, 0, 12, 0, 0, 0, 2, 0, 0, 0, 12, 0, 0, 0, 3, 0, 0, 0, 2, 0, 0, 0, 5, 0, 0, 0, 13, 0, 0, 0, 2, 0, 0, 0, 13, 0, 0, 0, 14, 0, 0, 0, 2, 0, 0, 0, 14, 0, 0, 0, 9, 0, 0, 0, 5, 0, 0, 0, 8, 0, 0, 0, 17, 0, 0, 0, 5, 0, 0, 0, 17, 0, 0, 0, 25, 0, 0, 0, 5, 0, 0, 0, 25, 0, 0, 0, 24, 0, 0, 0, 5, 0, 0, 0, 24, 0, 0, 0, 23, 0, 0, 0, 5, 0, 0, 0, 23, 0, 0, 0, 39, 0, 0, 0, 5, 0, 0, 0, 39, 0, 0, 0, 38, 0, 0, 0, 5, 0, 0, 0, 38, 0, 0, 0, 37, 0, 0, 0, 5, 0, 0, 0, 37, 0, 0, 0, 36, 0, 0, 0, 5, 0, 0, 0, 36, 0, 0, 0, 41, 0, 0, 0, 5, 0, 0, 0, 41, 0, 0, 0, 30, 0, 0, 0, 5, 0, 0, 0, 30, 0, 0, 0, 29, 0, 0, 0, 5, 0, 0, 0, 29, 0, 0, 0, 20, 0, 0, 0, 5, 0, 0, 0, 20, 0, 0, 0, 14, 0, 0, 0, 5, 0, 0, 0, 14, 0, 0, 0, 13, 0, 0, 0, 6, 0, 0, 0, 15, 0, 0, 0, 16, 0, 0, 0, 6, 0, 0, 0, 16, 0, 0, 0, 7, 0, 0, 0, 7, 0, 0, 0, 16, 0, 0, 0, 17, 0, 0, 0, 7, 0, 0, 0, 17, 0, 0, 0, 8, 0, 0, 0, 9, 0, 0, 0, 14, 0, 0, 0, 18, 0, 0, 0, 9, 0, 0, 0, 18, 0, 0, 0, 10, 0, 0, 0, 10, 0, 0, 0, 19, 0, 0, 0, 11, 0, 0, 0, 10, 0, 0, 0, 18, 0, 0, 0, 19, 0, 0, 0, 11, 0, 0, 0, 19, 0, 0, 0, 12, 0, 0, 0, 14, 0, 0, 0, 20, 0, 0, 0, 18, 0, 0, 0, 15, 0, 0, 0, 21, 0, 0, 0, 16, 0, 0, 0, 16, 0, 0, 0, 22, 0, 0, 0, 23, 0, 0, 0, 16, 0, 0, 0, 23, 0, 0, 0, 24, 0, 0, 0, 16, 0, 0, 0, 24, 0, 0, 0, 25, 0, 0, 0, 16, 0, 0, 0, 25, 0, 0, 0, 17, 0, 0, 0, 16, 0, 0, 0, 21, 0, 0, 0, 22, 0, 0, 0, 18, 0, 0, 0, 26, 0, 0, 0, 27, 0, 0, 0, 18, 0, 0, 0, 27, 0, 0, 0, 28, 0, 0, 0, 18, 0, 0, 0, 28, 0, 0, 0, 19, 0, 0, 0, 18, 0, 0, 0, 20, 0, 0, 0, 29, 0, 0, 0, 18, 0, 0, 0, 29, 0, 0, 0, 30, 0, 0, 0, 18, 0, 0, 0, 30, 0, 0, 0, 31, 0, 0, 0, 18, 0, 0, 0, 31, 0, 0, 0, 26, 0, 0, 0, 21, 0, 0, 0, 32, 0, 0, 0, 22, 0, 0, 0, 22, 0, 0, 0, 32, 0, 0, 0, 33, 0, 0, 0, 22, 0, 0, 0, 33, 0, 0, 0, 34, 0, 0, 0, 22, 0, 0, 0, 34, 0, 0, 0, 35, 0, 0, 0, 22, 0, 0, 0, 35, 0, 0, 0, 36, 0, 0, 0, 22, 0, 0, 0, 36, 0, 0, 0, 37, 0, 0, 0, 22, 0, 0, 0, 37, 0, 0, 0, 38, 0, 0, 0, 22, 0, 0, 0, 38, 0, 0, 0, 39, 0, 0, 0, 22, 0, 0, 0, 39, 0, 0, 0, 23, 0, 0, 0, 26, 0, 0, 0, 31, 0, 0, 0, 27, 0, 0, 0, 27, 0, 0, 0, 31, 0, 0, 0, 40, 0, 0, 0, 30, 0, 0, 0, 41, 0, 0, 0, 31, 0, 0, 0, 31, 0, 0, 0, 41, 0, 0, 0, 35, 0, 0, 0, 31, 0, 0, 0, 35, 0, 0, 0, 34, 0, 0, 0, 31, 0, 0, 0, 34, 0, 0, 0, 42, 0, 0, 0, 31, 0, 0, 0, 42, 0, 0, 0, 40, 0, 0, 0, 35, 0, 0, 0, 41, 0, 0, 0, 36, 0, 0, 0, 16, 0, 0, 0, 0, 0, 0, 0, 0, 0, 0, 0, 0, 0, 0, 0, 0, 0, 0, 0, 16, 0, 0, 0, 0, 0, 0, 0, 0, 0, 0, 0, 0, 0, 0, 0, 0, 0, 128, 63, 105, 0, 0, 0, 4, 0, 0, 0, 168, 197, 219, 189, 32, 117, 206, 187, 0, 0, 0, 0, 208, 121, 215, 189, 0, 0, 0, 0, 0, 0, 208, 183, 189, 253, 119, 190, 87, 24, 210, 190, 0, 0, 0, 0, 0, 72, 246, 185, 72, 157, 233, 190, 0, 0, 0, 0, 126, 6, 216, 189, 0, 0, 0, 0, 102, 199, 86, 189, 0, 72, 246, 185, 0, 0, 0, 0, 89, 129, 216, 189, 111, 93, 121, 190, 158, 2, 211, 190, 110, 48, 102, 190, 151, 15, 126, 190, 215, 84, 218, 190, 201, 213, 106, 190, 6, 3, 125, 190, 106, 20, 218, 190, 0, 0, 0, 0, 112, 70, 216, 189, 0, 0, 0, 0, 202, 163, 169, 189, 88, 122, 106, 190, 145, 145, 233, 190, 0, 0, 0, 0, 102, 187, 101, 190, 145, 186, 233, 190, 158, 81, 112, 190, 0, 72, 246, 185, 182, 180, 233, 190, 166, 64, 111, 190, 0, 72, 246, 185, 191, 179, 229, 189, 119, 167, 19, 190, 61, 246, 173, 189, 0, 0, 0, 0, 96, 164, 215, 189, 56, 218, 184, 189, 0, 0, 0, 0, 184, 94, 204, 189, 127, 71, 47, 190, 217, 93, 134, 190, 94, 146, 71, 190, 120, 207, 97, 190, 12, 26, 211, 190, 195, 222, 123, 190, 107, 9, 125, 190, 33, 32, 218, 190, 0, 0, 0, 0, 228, 52, 102, 190, 215, 84, 218, 190, 142, 85, 128, 190, 214, 168, 127, 190, 125, 16, 226, 190, 61, 85, 108, 190, 219, 196, 116, 190, 44, 203, 229, 190, 0, 0, 0, 0, 246, 255, 109, 190, 182, 180, 233, 190, 212, 118, 105, 190, 0, 72, 246, 185, 182, 180, 233, 190, 166, 90, 111, 190, 38, 219, 102, 190, 154, 226, 229, 190, 213, 136, 121, 190, 0, 72, 246, 185, 52, 28, 226, 190, 4, 174, 129, 190, 0, 72, 246, 185, 154, 226, 229, 190, 84, 169, 121, 190, 0, 72, 246, 185, 122, 223, 210, 190, 186, 239, 124, 190, 0, 123, 65, 186, 122, 223, 210, 190, 186, 239, 124, 190, 170, 162, 126, 190, 89, 237, 225, 190, 0, 0, 0, 0, 0, 224, 71, 186, 69, 67, 218, 190, 138, 228, 128, 190, 244, 186, 103, 190, 52, 28, 226, 190, 200, 27, 129, 190, 138, 23, 119, 190, 154, 226, 229, 190, 200, 252, 106, 190, 224, 149, 126, 190, 16, 249, 225, 190, 0, 0, 0, 0, 0, 72, 246, 185, 69, 67, 218, 190, 138, 228, 128, 190, 198, 0, 0, 0, 0, 0, 0, 0, 1, 0, 0, 0, 2, 0, 0, 0, 0, 0, 0, 0, 2, 0, 0, 0, 8, 0, 0, 0, 0, 0, 0, 0, 8, 0, 0, 0, 18, 0, 0, 0, 0, 0, 0, 0, 18, 0, 0, 0, 29, 0, 0, 0, 0, 0, 0, 0, 29, 0, 0, 0, 33, 0, 0, 0, 0, 0, 0, 0, 33, 0, 0, 0, 21, 0, 0, 0, 0, 0, 0, 0, 21, 0, 0, 0, 10, 0, 0, 0, 0, 0, 0, 0, 10, 0, 0, 0, 3, 0, 0, 0, 0, 0, 0, 0, 3, 0, 0, 0, 1, 0, 0, 0, 1, 0, 0, 0, 4, 0, 0, 0, 2, 0, 0, 0, 1, 0, 0, 0, 3, 0, 0, 0, 5, 0, 0, 0, 1, 0, 0, 0, 5, 0, 0, 0, 14, 0, 0, 0, 1, 0, 0, 0, 14, 0, 0, 0, 15, 0, 0, 0, 1, 0, 0, 0, 15, 0, 0, 0, 9, 0, 0, 0, 1, 0, 0, 0, 9, 0, 0, 0, 4, 0, 0, 0, 2, 0, 0, 0, 6, 0, 0, 0, 7, 0, 0, 0, 2, 0, 0, 0, 7, 0, 0, 0, 8, 0, 0, 0, 2, 0, 0, 0, 4, 0, 0, 0, 9, 0, 0, 0, 2, 0, 0, 0, 9, 0, 0, 0, 6, 0, 0, 0, 3, 0, 0, 0, 10, 0, 0, 0, 11, 0, 0, 0, 3, 0, 0, 0, 11, 0, 0, 0, 12, 0, 0, 0, 3, 0, 0, 0, 12, 0, 0, 0, 23, 0, 0, 0, 3, 0, 0, 0, 23, 0, 0, 0, 26, 0, 0, 0, 3, 0, 0, 0, 26, 0, 0, 0, 25, 0, 0, 0, 3, 0, 0, 0, 25, 0, 0, 0, 34, 0, 0, 0, 3, 0, 0, 0, 34, 0, 0, 0, 27, 0, 0, 0, 3, 0, 0, 0, 27, 0, 0, 0, 13, 0, 0, 0, 3, 0, 0, 0, 13, 0, 0, 0, 5, 0, 0, 0, 5, 0, 0, 0, 13, 0, 0, 0, 14, 0, 0, 0, 6, 0, 0, 0, 9, 0, 0, 0, 15, 0, 0, 0, 6, 0, 0, 0, 15, 0, 0, 0, 14, 0, 0, 0, 6, 0, 0, 0, 14, 0, 0, 0, 16, 0, 0, 0, 6, 0, 0, 0, 16, 0, 0, 0, 17, 0, 0, 0, 6, 0, 0, 0, 17, 0, 0, 0, 7, 0, 0, 0, 7, 0, 0, 0, 18, 0, 0, 0, 8, 0, 0, 0, 7, 0, 0, 0, 17, 0, 0, 0, 19, 0, 0, 0, 7, 0, 0, 0, 19, 0, 0, 0, 20, 0, 0, 0, 7, 0, 0, 0, 20, 0, 0, 0, 18, 0, 0, 0, 10, 0, 0, 0, 21, 0, 0, 0, 22, 0, 0, 0, 10, 0, 0, 0, 22, 0, 0, 0, 11, 0, 0, 0, 11, 0, 0, 0, 23, 0, 0, 0, 12, 0, 0, 0, 11, 0, 0, 0, 22, 0, 0, 0, 24, 0, 0, 0, 11, 0, 0, 0, 24, 0, 0, 0, 25, 0, 0, 0, 11, 0, 0, 0, 25, 0, 0, 0, 26, 0, 0, 0, 11, 0, 0, 0, 26, 0, 0, 0, 23, 0, 0, 0, 13, 0, 0, 0, 27, 0, 0, 0, 28, 0, 0, 0, 13, 0, 0, 0, 28, 0, 0, 0, 16, 0, 0, 0, 13, 0, 0, 0, 16, 0, 0, 0, 14, 0, 0, 0, 16, 0, 0, 0, 28, 0, 0, 0, 17, 0, 0, 0, 17, 0, 0, 0, 28, 0, 0, 0, 19, 0, 0, 0, 18, 0, 0, 0, 20, 0, 0, 0, 29, 0, 0, 0, 19, 0, 0, 0, 30, 0, 0, 0, 25, 0, 0, 0, 19, 0, 0, 0, 25, 0, 0, 0, 31, 0, 0, 0, 19, 0, 0, 0, 31, 0, 0, 0, 20, 0, 0, 0, 19, 0, 0, 0, 28, 0, 0, 0, 30, 0, 0, 0, 20, 0, 0, 0, 31, 0, 0, 0, 32, 0, 0, 0, 20, 0, 0, 0, 32, 0, 0, 0, 33, 0, 0, 0, 20, 0, 0, 0, 33, 0, 0, 0, 29, 0, 0, 0, 21, 0, 0, 0, 33, 0, 0, 0, 22, 0, 0, 0, 22, 0, 0, 0, 33, 0, 0, 0, 32, 0, 0, 0, 22, 0, 0, 0, 32, 0, 0, 0, 24, 0, 0, 0, 24, 0, 0, 0, 32, 0, 0, 0, 31, 0, 0, 0, 24, 0, 0, 0, 31, 0, 0, 0, 25, 0, 0, 0, 25, 0, 0, 0, 30, 0, 0, 0, 34, 0, 0, 0, 27, 0, 0, 0, 34, 0, 0, 0, 30, 0, 0, 0, 27, 0, 0, 0, 30, 0, 0, 0, 28, 0, 0, 0, 16, 0, 0, 0, 0, 0, 0, 0, 0, 0, 0, 0, 0, 0, 0, 0, 0, 0, 0, 0, 16, 0, 0, 0, 0, 0, 0, 0, 0, 0, 0, 0, 0, 0, 0, 0, 0, 0, 128, 63, 111, 0, 0, 0, 4, 0, 0, 0, 130, 125, 101, 190, 24, 202, 225, 190, 6, 43, 130, 62, 219, 157, 125, 190, 206, 213, 225, 190, 220, 159, 110, 62, 50, 19, 117, 190, 169, 161, 229, 190, 137, 50, 109, 62, 77, 183, 100, 190, 169, 161, 229, 190, 242, 158, 123, 62, 0, 108, 2, 58, 24, 202, 225, 190, 220, 184, 129, 62, 0, 108, 2, 58, 176, 253, 217, 190, 93, 235, 128, 62, 70, 4, 100, 190, 64, 15, 218, 190, 68, 90, 129, 62, 168, 4, 124, 190, 64, 15, 218, 190, 100, 11, 109, 62, 205, 10, 125, 190, 246, 26, 218, 190, 128, 66, 140, 58, 0, 164, 126, 190, 19, 243, 225, 190, 128, 133, 143, 58, 70, 2, 108, 190, 95, 115, 233, 190, 151, 164, 107, 62, 54, 151, 126, 190, 238, 248, 225, 190, 0, 0, 0, 0, 40, 177, 99, 190, 95, 115, 233, 190, 228, 107, 114, 62, 0, 108, 2, 58, 132, 167, 229, 190, 49, 188, 121, 62, 0, 108, 2, 58, 146, 37, 210, 190, 106, 170, 124, 62, 95, 165, 95, 190, 91, 207, 210, 190, 8, 221, 125, 62, 209, 101, 119, 190, 240, 183, 210, 190, 130, 84, 104, 62, 152, 69, 120, 190, 26, 137, 210, 190, 128, 255, 136, 58, 205, 10, 125, 190, 246, 26, 218, 190, 0, 0, 0, 0, 155, 157, 126, 190, 94, 231, 225, 190, 0, 0, 0, 0, 220, 117, 106, 190, 128, 150, 233, 190, 0, 0, 0, 0, 220, 117, 106, 190, 128, 150, 233, 190, 128, 255, 136, 58, 121, 198, 116, 190, 164, 202, 229, 190, 0, 0, 0, 0, 0, 108, 2, 58, 53, 162, 233, 190, 0, 192, 80, 56, 0, 108, 2, 58, 95, 115, 233, 190, 36, 119, 111, 62, 0, 108, 2, 58, 0, 0, 0, 0, 199, 223, 214, 61, 72, 216, 91, 189, 0, 0, 0, 0, 40, 72, 215, 61, 82, 152, 45, 190, 221, 38, 134, 190, 33, 187, 72, 62, 178, 79, 172, 189, 0, 0, 0, 0, 89, 124, 215, 61, 186, 89, 183, 189, 0, 0, 0, 0, 224, 56, 204, 61, 51, 248, 214, 189, 0, 0, 0, 0, 240, 222, 169, 61, 152, 69, 120, 190, 207, 148, 210, 190, 0, 0, 0, 0, 35, 56, 215, 189, 0, 0, 0, 0, 126, 145, 86, 61, 104, 50, 69, 190, 6, 248, 133, 190, 0, 0, 0, 0, 223, 248, 119, 190, 184, 31, 210, 190, 0, 0, 0, 0, 184, 111, 105, 190, 128, 150, 233, 190, 0, 0, 0, 0, 220, 132, 215, 189, 0, 0, 0, 0, 0, 0, 0, 0, 210, 0, 0, 0, 0, 0, 0, 0, 1, 0, 0, 0, 2, 0, 0, 0, 0, 0, 0, 0, 2, 0, 0, 0, 3, 0, 0, 0, 0, 0, 0, 0, 3, 0, 0, 0, 4, 0, 0, 0, 0, 0, 0, 0, 4, 0, 0, 0, 5, 0, 0, 0, 0, 0, 0, 0, 5, 0, 0, 0, 6, 0, 0, 0, 0, 0, 0, 0, 6, 0, 0, 0, 1, 0, 0, 0, 1, 0, 0, 0, 6, 0, 0, 0, 7, 0, 0, 0, 1, 0, 0, 0, 7, 0, 0, 0, 8, 0, 0, 0, 1, 0, 0, 0, 8, 0, 0, 0, 9, 0, 0, 0, 1, 0, 0, 0, 9, 0, 0, 0, 2, 0, 0, 0, 2, 0, 0, 0, 10, 0, 0, 0, 3, 0, 0, 0, 2, 0, 0, 0, 9, 0, 0, 0, 11, 0, 0, 0, 2, 0, 0, 0, 11, 0, 0, 0, 10, 0, 0, 0, 3, 0, 0, 0, 10, 0, 0, 0, 12, 0, 0, 0, 3, 0, 0, 0, 12, 0, 0, 0, 4, 0, 0, 0, 4, 0, 0, 0, 12, 0, 0, 0, 13, 0, 0, 0, 4, 0, 0, 0, 13, 0, 0, 0, 24, 0, 0, 0, 4, 0, 0, 0, 24, 0, 0, 0, 23, 0, 0, 0, 4, 0, 0, 0, 23, 0, 0, 0, 25, 0, 0, 0, 4, 0, 0, 0, 25, 0, 0, 0, 14, 0, 0, 0, 4, 0, 0, 0, 14, 0, 0, 0, 5, 0, 0, 0, 5, 0, 0, 0, 14, 0, 0, 0, 6, 0, 0, 0, 6, 0, 0, 0, 14, 0, 0, 0, 15, 0, 0, 0, 6, 0, 0, 0, 15, 0, 0, 0, 16, 0, 0, 0, 6, 0, 0, 0, 16, 0, 0, 0, 7, 0, 0, 0, 7, 0, 0, 0, 16, 0, 0, 0, 17, 0, 0, 0, 7, 0, 0, 0, 17, 0, 0, 0, 8, 0, 0, 0, 8, 0, 0, 0, 18, 0, 0, 0, 9, 0, 0, 0, 8, 0, 0, 0, 17, 0, 0, 0, 18, 0, 0, 0, 9, 0, 0, 0, 18, 0, 0, 0, 19, 0, 0, 0, 9, 0, 0, 0, 19, 0, 0, 0, 11, 0, 0, 0, 10, 0, 0, 0, 20, 0, 0, 0, 21, 0, 0, 0, 10, 0, 0, 0, 21, 0, 0, 0, 12, 0, 0, 0, 10, 0, 0, 0, 11, 0, 0, 0, 22, 0, 0, 0, 10, 0, 0, 0, 22, 0, 0, 0, 20, 0, 0, 0, 11, 0, 0, 0, 19, 0, 0, 0, 18, 0, 0, 0, 11, 0, 0, 0, 18, 0, 0, 0, 31, 0, 0, 0, 11, 0, 0, 0, 31, 0, 0, 0, 34, 0, 0, 0, 11, 0, 0, 0, 34, 0, 0, 0, 33, 0, 0, 0, 11, 0, 0, 0, 33, 0, 0, 0, 36, 0, 0, 0, 11, 0, 0, 0, 36, 0, 0, 0, 35, 0, 0, 0, 11, 0, 0, 0, 35, 0, 0, 0, 20, 0, 0, 0, 11, 0, 0, 0, 20, 0, 0, 0, 22, 0, 0, 0, 12, 0, 0, 0, 21, 0, 0, 0, 23, 0, 0, 0, 12, 0, 0, 0, 23, 0, 0, 0, 24, 0, 0, 0, 12, 0, 0, 0, 24, 0, 0, 0, 13, 0, 0, 0, 14, 0, 0, 0, 25, 0, 0, 0, 26, 0, 0, 0, 14, 0, 0, 0, 26, 0, 0, 0, 27, 0, 0, 0, 14, 0, 0, 0, 27, 0, 0, 0, 15, 0, 0, 0, 15, 0, 0, 0, 27, 0, 0, 0, 28, 0, 0, 0, 15, 0, 0, 0, 28, 0, 0, 0, 16, 0, 0, 0, 16, 0, 0, 0, 28, 0, 0, 0, 29, 0, 0, 0, 16, 0, 0, 0, 29, 0, 0, 0, 30, 0, 0, 0, 16, 0, 0, 0, 30, 0, 0, 0, 17, 0, 0, 0, 17, 0, 0, 0, 31, 0, 0, 0, 18, 0, 0, 0, 17, 0, 0, 0, 30, 0, 0, 0, 32, 0, 0, 0, 17, 0, 0, 0, 32, 0, 0, 0, 33, 0, 0, 0, 17, 0, 0, 0, 33, 0, 0, 0, 34, 0, 0, 0, 17, 0, 0, 0, 34, 0, 0, 0, 31, 0, 0, 0, 20, 0, 0, 0, 23, 0, 0, 0, 21, 0, 0, 0, 20, 0, 0, 0, 35, 0, 0, 0, 23, 0, 0, 0, 23, 0, 0, 0, 35, 0, 0, 0, 36, 0, 0, 0, 23, 0, 0, 0, 36, 0, 0, 0, 25, 0, 0, 0, 25, 0, 0, 0, 36, 0, 0, 0, 32, 0, 0, 0, 25, 0, 0, 0, 32, 0, 0, 0, 30, 0, 0, 0, 25, 0, 0, 0, 30, 0, 0, 0, 29, 0, 0, 0, 25, 0, 0, 0, 29, 0, 0, 0, 28, 0, 0, 0, 25, 0, 0, 0, 28, 0, 0, 0, 26, 0, 0, 0, 26, 0, 0, 0, 28, 0, 0, 0, 27, 0, 0, 0, 32, 0, 0, 0, 36, 0, 0, 0, 33, 0, 0, 0, 16, 0, 0, 0, 0, 0, 0, 0, 0, 0, 0, 0, 0, 0, 0, 0, 0, 0, 0, 0, 16, 0, 0, 0, 0, 0, 0, 0, 0, 0, 0, 0, 0, 0, 0, 0, 0, 0, 128, 63, 108, 0, 0, 0, 4, 0, 0, 0, 0, 51, 15, 58, 167, 199, 225, 190, 126, 182, 129, 62, 0, 51, 15, 58, 130, 205, 225, 190, 126, 182, 129, 62, 192, 67, 196, 58, 130, 205, 225, 190, 126, 182, 129, 62, 236, 60, 101, 62, 130, 205, 225, 190, 189, 55, 129, 62, 186, 195, 99, 62, 163, 6, 218, 190, 251, 106, 128, 62, 192, 67, 196, 58, 200, 0, 218, 190, 124, 230, 128, 62, 0, 51, 15, 58, 200, 0, 218, 190, 124, 230, 128, 62, 0, 51, 15, 58, 60, 165, 229, 190, 228, 185, 121, 62, 33, 222, 96, 62, 63, 113, 233, 190, 80, 147, 113, 62, 76, 42, 99, 62, 134, 153, 229, 190, 102, 66, 122, 62, 214, 168, 127, 62, 93, 211, 225, 190, 166, 46, 96, 62, 72, 9, 126, 62, 126, 12, 218, 190, 34, 175, 94, 62, 240, 100, 95, 62, 114, 198, 210, 190, 106, 22, 124, 62, 0, 51, 15, 58, 126, 34, 210, 190, 108, 165, 124, 62, 0, 51, 15, 58, 63, 113, 233, 190, 203, 119, 111, 62, 38, 33, 109, 62, 26, 119, 233, 190, 36, 75, 95, 62, 136, 158, 118, 62, 60, 165, 229, 190, 36, 205, 95, 62, 28, 169, 126, 62, 53, 2, 226, 190, 0, 0, 208, 55, 28, 169, 126, 62, 127, 246, 225, 190, 0, 0, 208, 55, 244, 15, 125, 62, 124, 53, 218, 190, 0, 0, 208, 55, 139, 4, 120, 62, 126, 34, 210, 190, 0, 0, 208, 55, 96, 87, 121, 62, 188, 186, 210, 190, 150, 22, 90, 62, 146, 44, 228, 61, 0, 0, 0, 0, 172, 229, 174, 61, 144, 176, 213, 61, 0, 0, 0, 0, 202, 173, 186, 61, 172, 86, 168, 61, 0, 0, 0, 0, 13, 39, 214, 61, 0, 51, 15, 58, 55, 232, 227, 189, 104, 208, 18, 62, 0, 51, 15, 58, 23, 160, 233, 190, 0, 1, 15, 58, 184, 155, 105, 62, 205, 171, 233, 190, 0, 0, 208, 55, 12, 149, 106, 62, 242, 165, 233, 190, 0, 0, 208, 55, 104, 229, 116, 62, 20, 212, 229, 190, 0, 0, 208, 55, 52, 83, 227, 61, 0, 0, 0, 0, 0, 0, 208, 55, 218, 223, 227, 61, 0, 0, 0, 0, 40, 148, 97, 61, 128, 243, 59, 58, 0, 0, 0, 0, 15, 221, 214, 61, 0, 51, 15, 58, 0, 0, 0, 0, 15, 221, 214, 61, 0, 51, 15, 58, 23, 160, 233, 190, 0, 0, 156, 56, 240, 254, 23, 60, 23, 160, 233, 190, 0, 0, 208, 55, 204, 0, 0, 0, 0, 0, 0, 0, 1, 0, 0, 0, 2, 0, 0, 0, 0, 0, 0, 0, 2, 0, 0, 0, 3, 0, 0, 0, 0, 0, 0, 0, 3, 0, 0, 0, 4, 0, 0, 0, 0, 0, 0, 0, 4, 0, 0, 0, 5, 0, 0, 0, 0, 0, 0, 0, 5, 0, 0, 0, 6, 0, 0, 0, 0, 0, 0, 0, 6, 0, 0, 0, 13, 0, 0, 0, 0, 0, 0, 0, 13, 0, 0, 0, 25, 0, 0, 0, 0, 0, 0, 0, 25, 0, 0, 0, 33, 0, 0, 0, 0, 0, 0, 0, 33, 0, 0, 0, 34, 0, 0, 0, 0, 0, 0, 0, 34, 0, 0, 0, 26, 0, 0, 0, 0, 0, 0, 0, 26, 0, 0, 0, 14, 0, 0, 0, 0, 0, 0, 0, 14, 0, 0, 0, 7, 0, 0, 0, 0, 0, 0, 0, 7, 0, 0, 0, 1, 0, 0, 0, 1, 0, 0, 0, 7, 0, 0, 0, 8, 0, 0, 0, 1, 0, 0, 0, 8, 0, 0, 0, 2, 0, 0, 0, 2, 0, 0, 0, 8, 0, 0, 0, 9, 0, 0, 0, 2, 0, 0, 0, 9, 0, 0, 0, 3, 0, 0, 0, 3, 0, 0, 0, 9, 0, 0, 0, 10, 0, 0, 0, 3, 0, 0, 0, 10, 0, 0, 0, 4, 0, 0, 0, 4, 0, 0, 0, 11, 0, 0, 0, 12, 0, 0, 0, 4, 0, 0, 0, 12, 0, 0, 0, 13, 0, 0, 0, 4, 0, 0, 0, 13, 0, 0, 0, 5, 0, 0, 0, 4, 0, 0, 0, 10, 0, 0, 0, 11, 0, 0, 0, 5, 0, 0, 0, 13, 0, 0, 0, 6, 0, 0, 0, 7, 0, 0, 0, 14, 0, 0, 0, 8, 0, 0, 0, 8, 0, 0, 0, 15, 0, 0, 0, 16, 0, 0, 0, 8, 0, 0, 0, 16, 0, 0, 0, 10, 0, 0, 0, 8, 0, 0, 0, 10, 0, 0, 0, 9, 0, 0, 0, 8, 0, 0, 0, 14, 0, 0, 0, 15, 0, 0, 0, 10, 0, 0, 0, 16, 0, 0, 0, 17, 0, 0, 0, 10, 0, 0, 0, 17, 0, 0, 0, 18, 0, 0, 0, 10, 0, 0, 0, 18, 0, 0, 0, 19, 0, 0, 0, 10, 0, 0, 0, 19, 0, 0, 0, 11, 0, 0, 0, 11, 0, 0, 0, 20, 0, 0, 0, 21, 0, 0, 0, 11, 0, 0, 0, 21, 0, 0, 0, 22, 0, 0, 0, 11, 0, 0, 0, 22, 0, 0, 0, 12, 0, 0, 0, 11, 0, 0, 0, 19, 0, 0, 0, 20, 0, 0, 0, 12, 0, 0, 0, 22, 0, 0, 0, 23, 0, 0, 0, 12, 0, 0, 0, 23, 0, 0, 0, 24, 0, 0, 0, 12, 0, 0, 0, 24, 0, 0, 0, 13, 0, 0, 0, 13, 0, 0, 0, 24, 0, 0, 0, 25, 0, 0, 0, 14, 0, 0, 0, 26, 0, 0, 0, 27, 0, 0, 0, 14, 0, 0, 0, 27, 0, 0, 0, 15, 0, 0, 0, 15, 0, 0, 0, 27, 0, 0, 0, 28, 0, 0, 0, 15, 0, 0, 0, 28, 0, 0, 0, 29, 0, 0, 0, 15, 0, 0, 0, 29, 0, 0, 0, 17, 0, 0, 0, 15, 0, 0, 0, 17, 0, 0, 0, 16, 0, 0, 0, 17, 0, 0, 0, 29, 0, 0, 0, 28, 0, 0, 0, 17, 0, 0, 0, 28, 0, 0, 0, 27, 0, 0, 0, 17, 0, 0, 0, 27, 0, 0, 0, 35, 0, 0, 0, 17, 0, 0, 0, 35, 0, 0, 0, 30, 0, 0, 0, 17, 0, 0, 0, 30, 0, 0, 0, 20, 0, 0, 0, 17, 0, 0, 0, 20, 0, 0, 0, 19, 0, 0, 0, 17, 0, 0, 0, 19, 0, 0, 0, 18, 0, 0, 0, 20, 0, 0, 0, 30, 0, 0, 0, 31, 0, 0, 0, 20, 0, 0, 0, 31, 0, 0, 0, 22, 0, 0, 0, 20, 0, 0, 0, 22, 0, 0, 0, 21, 0, 0, 0, 22, 0, 0, 0, 31, 0, 0, 0, 30, 0, 0, 0, 22, 0, 0, 0, 30, 0, 0, 0, 33, 0, 0, 0, 22, 0, 0, 0, 33, 0, 0, 0, 32, 0, 0, 0, 22, 0, 0, 0, 32, 0, 0, 0, 24, 0, 0, 0, 22, 0, 0, 0, 24, 0, 0, 0, 23, 0, 0, 0, 24, 0, 0, 0, 32, 0, 0, 0, 25, 0, 0, 0, 25, 0, 0, 0, 32, 0, 0, 0, 33, 0, 0, 0, 26, 0, 0, 0, 34, 0, 0, 0, 27, 0, 0, 0, 27, 0, 0, 0, 34, 0, 0, 0, 35, 0, 0, 0, 30, 0, 0, 0, 35, 0, 0, 0, 34, 0, 0, 0, 30, 0, 0, 0, 34, 0, 0, 0, 33, 0, 0, 0, 16, 0, 0, 0, 0, 0, 0, 0, 0, 0, 0, 0, 0, 0, 0, 0, 0, 0, 0, 0, 16, 0, 0, 0, 0, 0, 0, 0, 0, 0, 0, 0, 0, 0, 0, 0, 0, 0, 128, 63, 105, 0, 0, 0, 4, 0, 0, 0, 253, 86, 227, 61, 0, 0, 0, 0, 0, 0, 0, 0, 216, 0, 120, 62, 38, 42, 210, 190, 0, 0, 0, 0, 248, 83, 120, 62, 74, 159, 210, 190, 128, 66, 140, 186, 253, 86, 227, 61, 0, 0, 0, 0, 0, 230, 119, 186, 0, 72, 246, 185, 0, 0, 0, 0, 88, 142, 216, 189, 0, 72, 246, 185, 139, 157, 233, 190, 0, 0, 0, 0, 79, 25, 125, 62, 242, 49, 218, 190, 0, 0, 0, 0, 79, 25, 125, 62, 242, 49, 218, 190, 128, 66, 140, 186, 237, 31, 124, 62, 22, 85, 218, 190, 5, 208, 96, 190, 244, 128, 119, 62, 36, 247, 210, 190, 59, 51, 92, 190, 215, 233, 21, 62, 109, 111, 230, 189, 134, 23, 250, 189, 79, 202, 226, 61, 0, 0, 0, 0, 238, 82, 105, 189, 238, 227, 83, 61, 0, 0, 0, 0, 197, 3, 217, 189, 0, 72, 246, 185, 73, 41, 134, 190, 192, 82, 72, 190, 0, 72, 246, 185, 29, 175, 233, 190, 110, 60, 111, 190, 216, 204, 94, 62, 212, 186, 233, 190, 68, 93, 115, 190, 164, 157, 105, 62, 66, 169, 233, 190, 0, 0, 0, 0, 142, 178, 126, 62, 44, 255, 225, 190, 0, 0, 0, 0, 44, 185, 125, 62, 154, 22, 226, 190, 101, 74, 98, 190, 60, 140, 97, 62, 22, 85, 218, 190, 202, 96, 129, 190, 254, 57, 93, 62, 146, 14, 211, 190, 166, 253, 125, 190, 147, 125, 226, 61, 0, 0, 0, 0, 254, 136, 178, 189, 190, 87, 166, 61, 0, 0, 0, 0, 245, 55, 217, 189, 0, 72, 246, 185, 146, 188, 210, 190, 21, 216, 124, 190, 0, 72, 246, 185, 29, 175, 233, 190, 12, 93, 111, 190, 0, 72, 246, 185, 220, 226, 229, 190, 159, 168, 121, 190, 0, 72, 246, 185, 154, 22, 226, 190, 208, 171, 129, 190, 142, 255, 96, 62, 220, 226, 229, 190, 229, 26, 124, 190, 198, 180, 116, 62, 220, 226, 229, 190, 248, 212, 97, 190, 71, 61, 107, 62, 29, 175, 233, 190, 102, 56, 97, 190, 60, 138, 106, 62, 66, 169, 233, 190, 0, 0, 0, 0, 238, 231, 116, 62, 73, 209, 229, 190, 0, 0, 0, 0, 230, 11, 99, 62, 154, 22, 226, 190, 6, 43, 130, 190, 0, 72, 246, 185, 95, 73, 218, 190, 215, 228, 128, 190, 150, 13, 212, 61, 0, 0, 0, 0, 204, 39, 190, 189, 198, 0, 0, 0, 0, 0, 0, 0, 1, 0, 0, 0, 2, 0, 0, 0, 0, 0, 0, 0, 2, 0, 0, 0, 3, 0, 0, 0, 0, 0, 0, 0, 3, 0, 0, 0, 11, 0, 0, 0, 0, 0, 0, 0, 11, 0, 0, 0, 21, 0, 0, 0, 0, 0, 0, 0, 21, 0, 0, 0, 34, 0, 0, 0, 0, 0, 0, 0, 34, 0, 0, 0, 22, 0, 0, 0, 0, 0, 0, 0, 22, 0, 0, 0, 12, 0, 0, 0, 0, 0, 0, 0, 12, 0, 0, 0, 4, 0, 0, 0, 0, 0, 0, 0, 4, 0, 0, 0, 5, 0, 0, 0, 0, 0, 0, 0, 5, 0, 0, 0, 16, 0, 0, 0, 0, 0, 0, 0, 16, 0, 0, 0, 30, 0, 0, 0, 0, 0, 0, 0, 30, 0, 0, 0, 31, 0, 0, 0, 0, 0, 0, 0, 31, 0, 0, 0, 17, 0, 0, 0, 0, 0, 0, 0, 17, 0, 0, 0, 6, 0, 0, 0, 0, 0, 0, 0, 6, 0, 0, 0, 1, 0, 0, 0, 1, 0, 0, 0, 6, 0, 0, 0, 2, 0, 0, 0, 2, 0, 0, 0, 6, 0, 0, 0, 7, 0, 0, 0, 2, 0, 0, 0, 7, 0, 0, 0, 8, 0, 0, 0, 2, 0, 0, 0, 8, 0, 0, 0, 9, 0, 0, 0, 2, 0, 0, 0, 9, 0, 0, 0, 10, 0, 0, 0, 2, 0, 0, 0, 10, 0, 0, 0, 3, 0, 0, 0, 3, 0, 0, 0, 10, 0, 0, 0, 11, 0, 0, 0, 4, 0, 0, 0, 12, 0, 0, 0, 13, 0, 0, 0, 4, 0, 0, 0, 13, 0, 0, 0, 23, 0, 0, 0, 4, 0, 0, 0, 23, 0, 0, 0, 33, 0, 0, 0, 4, 0, 0, 0, 33, 0, 0, 0, 26, 0, 0, 0, 4, 0, 0, 0, 26, 0, 0, 0, 25, 0, 0, 0, 4, 0, 0, 0, 25, 0, 0, 0, 24, 0, 0, 0, 4, 0, 0, 0, 24, 0, 0, 0, 14, 0, 0, 0, 4, 0, 0, 0, 14, 0, 0, 0, 5, 0, 0, 0, 5, 0, 0, 0, 14, 0, 0, 0, 15, 0, 0, 0, 5, 0, 0, 0, 15, 0, 0, 0, 16, 0, 0, 0, 6, 0, 0, 0, 17, 0, 0, 0, 7, 0, 0, 0, 7, 0, 0, 0, 17, 0, 0, 0, 18, 0, 0, 0, 7, 0, 0, 0, 18, 0, 0, 0, 8, 0, 0, 0, 8, 0, 0, 0, 19, 0, 0, 0, 20, 0, 0, 0, 8, 0, 0, 0, 20, 0, 0, 0, 9, 0, 0, 0, 8, 0, 0, 0, 18, 0, 0, 0, 19, 0, 0, 0, 9, 0, 0, 0, 20, 0, 0, 0, 10, 0, 0, 0, 10, 0, 0, 0, 20, 0, 0, 0, 21, 0, 0, 0, 10, 0, 0, 0, 21, 0, 0, 0, 11, 0, 0, 0, 12, 0, 0, 0, 22, 0, 0, 0, 20, 0, 0, 0, 12, 0, 0, 0, 20, 0, 0, 0, 13, 0, 0, 0, 13, 0, 0, 0, 20, 0, 0, 0, 23, 0, 0, 0, 14, 0, 0, 0, 24, 0, 0, 0, 15, 0, 0, 0, 15, 0, 0, 0, 24, 0, 0, 0, 25, 0, 0, 0, 15, 0, 0, 0, 25, 0, 0, 0, 26, 0, 0, 0, 15, 0, 0, 0, 26, 0, 0, 0, 27, 0, 0, 0, 15, 0, 0, 0, 27, 0, 0, 0, 18, 0, 0, 0, 15, 0, 0, 0, 18, 0, 0, 0, 28, 0, 0, 0, 15, 0, 0, 0, 28, 0, 0, 0, 29, 0, 0, 0, 15, 0, 0, 0, 29, 0, 0, 0, 30, 0, 0, 0, 15, 0, 0, 0, 30, 0, 0, 0, 16, 0, 0, 0, 17, 0, 0, 0, 31, 0, 0, 0, 29, 0, 0, 0, 17, 0, 0, 0, 29, 0, 0, 0, 28, 0, 0, 0, 17, 0, 0, 0, 28, 0, 0, 0, 18, 0, 0, 0, 18, 0, 0, 0, 32, 0, 0, 0, 19, 0, 0, 0, 18, 0, 0, 0, 27, 0, 0, 0, 32, 0, 0, 0, 19, 0, 0, 0, 32, 0, 0, 0, 33, 0, 0, 0, 19, 0, 0, 0, 33, 0, 0, 0, 20, 0, 0, 0, 20, 0, 0, 0, 22, 0, 0, 0, 34, 0, 0, 0, 20, 0, 0, 0, 34, 0, 0, 0, 21, 0, 0, 0, 20, 0, 0, 0, 33, 0, 0, 0, 23, 0, 0, 0, 26, 0, 0, 0, 33, 0, 0, 0, 32, 0, 0, 0, 26, 0, 0, 0, 32, 0, 0, 0, 27, 0, 0, 0, 29, 0, 0, 0, 31, 0, 0, 0, 30, 0, 0, 0]), hash: Hash(\"8de8816501635b8870d5e8c3d44c3af802110c61bd623ce584579e21605d338d\") })>",
  "PhysicsData": "<unsupported: BinaryString(BinaryString { buffer: [] })>",
  "PivotOffset": {
    "matrix": {
      "orientation": [
        [
          1.0,
          0.0,
          0.0
        ],
        [
          0.0,
          1.0,
          0.0
        ],
        [
          0.0,
          0.0,
          1.0
        ]
      ],
      "position": [
        0.0,
        0.0,
        0.0
      ]
    }
  },
  "Reflectance": 0.0,
  "RenderFidelity": "<unsupported: Enum(Enum { value: 1 })>",
  "RightParamA": -0.5,
  "RightParamB": 0.5,
  "RightSurface": "<unsupported: Enum(Enum { value: 0 })>",
  "RightSurfaceInput": "<unsupported: Enum(Enum { value: 0 })>",
  "RootPriority": 0,
  "RotVelocity": {
    "x": 0.0,
    "y": 0.0,
    "z": 0.0
  },
  "Sandboxed": false,
  "Size": {
    "x": 0.49933499097824097,
    "y": 0.9130069613456726,
    "z": 0.5084689855575562
  },
  "SourceAssetId": "<unsupported: Int64(3557782929)>",
  "Tags": "<unsupported: Tags(Tags { members: [] })>",
  "TextureContent": "<unsupported: Content(Content(Uri(\"rbxassetid://3557782878\")))>",
  "TopParamA": -0.5,
  "TopParamB": 0.5,
  "TopSurface": "<unsupported: Enum(Enum { value: 0 })>",
  "TopSurfaceInput": "<unsupported: Enum(Enum { value: 0 })>",
  "Transparency": 0.0,
  "UniqueId": "<unsupported: UniqueId(UniqueId { index: 3273404, time: 32318743, random: 7712671185636030641 })>",
  "UnscaledCofm": {
    "x": null,
    "y": null,
    "z": null
  },
  "UnscaledVolInertiaDiags": {
    "x": null,
    "y": null,
    "z": null
  },
  "UnscaledVolInertiaOffDiags": {
    "x": null,
    "y": null,
    "z": null
  },
  "UnscaledVolume": null,
  "Velocity": {
    "x": 0.0,
    "y": 0.0,
    "z": 0.0
  },
  "VertexCount": 0
}