{
  "Attributes": {},
  "Brightness": 3.0,
  "Capabilities": "<FAILED: Unsupported variant type: Discriminant(37) (property: Capabilities, class: PointLight, instance: PointLight)>",
  "Color": {
    "b": 0.9333333969116211,
    "g": 1.0,
    "r": 0.9215686917304993
  },
  "Enabled": true,
  "HistoryId": "<FAILED: Unsupported variant type: Discriminant(35) (property: HistoryId, class: PointLight, instance: PointLight)>",
  "Range": 20.0,
  "Sandboxed": false,
  "Shadows": true,
  "SourceAssetId": -1,
  "Tags": [],
  "UniqueId": "<FAILED: Unsupported variant type: Discriminant(35) (property: UniqueId, class: PointLight, instance: PointLight)>"
}